Workbook

Sheet dummy
A1: Order ID | B1: Order Date | C1: Ship Date | D1: Customer Name | E1: Segment | F1: Region | G1: Category | H1: Sub-Category | I1: Product Name | J1: Sales | K1: Quantity | L1: Discount | M1: Profit
A2: ORD-10001 | B2: 45177 | C2: 45178 | D2: Traci Sanchez | E2: Consumer | F2: North | G2: Office Supplies | H2: Binders | I2: Happy Binders | J2: 3720.67 | K2: 4 | L2: 0.05 | M2: -458.59
A3: ORD-10002 | B3: 46086 | C3: 46087 | D3: Norman Jordan | E3: Consumer | F3: South | G3: Office Supplies | H3: Paper | I3: Fight Paper | J3: 197.5 | K3: 4 | L3: 0.05 | M3: 15.39
A4: ORD-10003 | B4: 45235 | C4: 45244 | D4: Thomas Scott | E4: Consumer | F4: South | G4: Office Supplies | H4: Storage | I4: Process Storage | J4: 2126.62 | K4: 8 | L4: 0.2 | M4: -99.94
A5: ORD-10004 | B5: 45523 | C5: 45529 | D5: Samuel Diaz | E5: Corporate | F5: North | G5: Office Supplies | H5: Paper | I5: Prepare Paper | J5: 1425.46 | K5: 4 | L5: 0.1 | M5: -204.96
A6: ORD-10005 | B6: 45860 | C6: 45870 | D6: Tiffany Ruiz | E6: Consumer | F6: West | G6: Technology | H6: Accessories | I6: Coach Accessories | J6: 1359.38 | K6: 1 | M6: 71.62
A7: ORD-10006 | B7: 45335 | C7: 45340 | D7: Stephanie Rodriguez | E7: Home Office | F7: North | G7: Furniture | H7: Bookcases | I7: Task Bookcases | J7: 4155.55 | K7: 10 | L7: 0.1 | M7: 488.46
A8: ORD-10007 | B8: 46018 | C8: 46022 | D8: Barbara Mora | E8: Corporate | F8: East | G8: Furniture | H8: Bookcases | I8: Available Bookcases | J8: 3876.69 | K8: 2 | L8: 0.05 | M8: 1072.16
A9: ORD-10008 | B9: 45288 | C9: 45294 | D9: Gloria Brown | E9: Home Office | F9: North | G9: Technology | H9: Laptops | I9: Beautiful Laptops | J9: 855.14 | K9: 6 | L9: 0.05 | M9: 144.17
A10: ORD-10009 | B10: 45374 | C10: 45377 | D10: Stephen Adkins | E10: Corporate | F10: South | G10: Office Supplies | H10: Storage | I10: Purpose Storage | J10: 2693.99 | K10: 4 | L10: 0.05 | M10: 146.13
A11: ORD-10010 | B11: 46080 | C11: 46081 | D11: Rachel Mathews | E11: Consumer | F11: South | G11: Office Supplies | H11: Paper | I11: Last Paper | J11: 1183.79 | K11: 1 | L11: 0.1 | M11: 24.43
A12: ORD-10011 | B12: 45524 | C12: 45530 | D12: Jacqueline Johnson | E12: Home Office | F12: West | G12: Office Supplies | H12: Storage | I12: Prepare Storage | J12: 1102.5 | K12: 8 | L12: 0.15 | M12: 315.95
A13: ORD-10012 | B13: 45574 | C13: 45577 | D13: Kevin Anderson | E13: Home Office | F13: West | G13: Furniture | H13: Tables | I13: Live Tables | J13: 1270.81 | K13: 9 | L13: 0.2 | M13: -70.52
A14: ORD-10013 | B14: 45524 | C14: 45530 | D14: Kenneth Sullivan | E14: Consumer | F14: North | G14: Office Supplies | H14: Paper | I14: Example Paper | J14: 1135.64 | K14: 3 | L14: 0.2 | M14: 81.12
A15: ORD-10014 | B15: 45338 | C15: 45341 | D15: John Bates | E15: Corporate | F15: West | G15: Furniture | H15: Bookcases | I15: Individual Bookcases | J15: 3970.79 | K15: 7 | L15: 0.2 | M15: -655.42
A16: ORD-10015 | B16: 45214 | C16: 45223 | D16: Patrick Horn | E16: Home Office | F16: East | G16: Office Supplies | H16: Paper | I16: Tough Paper | J16: 4310.86 | K16: 1 | M16: 846.64
A17: ORD-10016 | B17: 45297 | C17: 45299 | D17: Danny Clark | E17: Home Office | F17: East | G17: Office Supplies | H17: Paper | I17: Cover Paper | J17: 1502.83 | K17: 3 | L17: 0.15 | M17: -297.88
A18: ORD-10017 | B18: 45233 | C18: 45242 | D18: Thomas Olson | E18: Consumer | F18: South | G18: Office Supplies | H18: Binders | I18: Thousand Binders | J18: 4567.51 | K18: 5 | M18: 361.81
A19: ORD-10018 | B19: 45669 | C19: 45678 | D19: Jeffrey Levy | E19: Corporate | F19: North | G19: Technology | H19: Phones | I19: Ahead Phones | J19: 4769.82 | K19: 9 | L19: 0 | M19: 617.31
A20: ORD-10019 | B20: 45262 | C20: 45267 | D20: James Hamilton | E20: Consumer | F20: West | G20: Furniture | H20: Tables | I20: Build Tables | J20: 1235.29 | K20: 4 | L20: 0.2 | M20: 396.31
A21: ORD-10020 | B21: 45662 | C21: 45665 | D21: Joshua Smith | E21: Home Office | F21: West | G21: Furniture | H21: Bookcases | I21: Cell Bookcases | J21: 685.54 | K21: 8 | L21: 0.2 | M21: -74.85
A22: ORD-10021 | B22: 46154 | C22: 46158 | D22: Lorraine Ruiz | E22: Corporate | F22: West | G22: Furniture | H22: Bookcases | I22: Suddenly Bookcases | J22: 3579.1 | K22: 7 | M22: 563.47
A23: ORD-10022 | B23: 45989 | C23: 45993 | D23: Terri Miller | E23: Home Office | F23: South | G23: Furniture | H23: Chairs | I23: Forget Chairs | J23: 366.93 | K23: 1 | L23: 0.2 | M23: 38.4
A24: ORD-10023 | B24: 45383 | C24: 45384 | D24: Stacey Lewis | E24: Consumer | F24: East | G24: Furniture | H24: Chairs | I24: Than Chairs | J24: 1183.26 | K24: 1 | L24: 0.1 | M24: -190.54
A25: ORD-10024 | B25: 45796 | C25: 45800 | D25: Amanda Roberts | E25: Corporate | F25: West | G25: Office Supplies | H25: Paper | I25: Culture Paper | J25: 2719.21 | K25: 10 | L25: 0.2 | M25: 163.07
A26: ORD-10025 | B26: 45564 | C26: 45566 | D26: William Fernandez | E26: Home Office | F26: North | G26: Furniture | H26: Chairs | I26: Cultural Chairs | J26: 3311.96 | K26: 6 | L26: 0.15 | M26: 86.46
A27: ORD-10026 | B27: 45647 | C27: 45649 | D27: Nicholas Taylor | E27: Consumer | F27: West | G27: Office Supplies | H27: Storage | I27: Make Storage | J27: 350.03 | K27: 6 | L27: 0 | M27: -22.14
A28: ORD-10027 | B28: 45441 | C28: 45444 | D28: Amanda Roy | E28: Home Office | F28: North | G28: Furniture | H28: Tables | I28: His Tables | J28: 1428.8 | K28: 4 | L28: 0 | M28: 62.47
A29: ORD-10028 | B29: 45683 | C29: 45692 | D29: Charles Moore | E29: Corporate | F29: West | G29: Furniture | H29: Bookcases | I29: Yeah Bookcases | J29: 4188.34 | K29: 2 | L29: 0.05 | M29: -454.56
A30: ORD-10029 | B30: 45352 | C30: 45353 | D30: Linda Wells | E30: Corporate | F30: East | G30: Furniture | H30: Tables | I30: Important Tables | J30: 864.95 | K30: 1 | L30: 0.15 | M30: -46.83
A31: ORD-10030 | B31: 45088 | C31: 45097 | D31: Daniel King | E31: Consumer | F31: North | G31: Technology | H31: Laptops | I31: Themselves Laptops | J31: 3326.26 | K31: 8 | L31: 0.05 | M31: -317.84
A32: ORD-10031 | B32: 46145 | C32: 46154 | D32: Ricardo Ramirez | E32: Corporate | F32: South | G32: Office Supplies | H32: Storage | I32: Growth Storage | J32: 351.74 | K32: 6 | L32: 0 | M32: -60.65
A33: ORD-10032 | B33: 45961 | C33: 45963 | D33: Erika Ellis | E33: Consumer | F33: West | G33: Furniture | H33: Bookcases | I33: One Bookcases | J33: 4264.15 | K33: 2 | L33: 0.2 | M33: -693.44
A34: ORD-10033 | B34: 46008 | C34: 46012 | D34: Pamela Norman | E34: Home Office | F34: East | G34: Furniture | H34: Bookcases | I34: Wait Bookcases | J34: 2915.65 | K34: 1 | L34: 0.2 | M34: -451.66
... A37: ORD-10036 | B37: 45724 | C37: 45726 | D37: Katelyn Williams | E37: Home Office | F37: East | G37: Furniture | H37: Tables | I37: Son Tables | J37: 4402.39 | K37: 6 | L37: 0.1 | M37: -498.52
A38: ORD-10037 | B38: 07-11-2023 | C38: 45246 | D38: Shannon Wagner | E38: Consumer | F38: South | G38: Office Supplies | H38: Storage | I38: With Storage | J38: 88.72 | K38: 9 | L38: 0.1 | M38: 27.72
A39: ORD-10038 | B39: 45815 | C39: 45817 | D39: Kelli Johnson | E39: Consumer | F39: East | G39: Technology | H39: Phones | I39: This Phones | J39: 3724.96 | K39: 3 | L39: 0.1 | M39: -167.75
A40: ORD-10039 | B40: 45087 | C40: 45092 | D40: Rebecca Blake | E40: Corporate | F40: East | G40: Furniture | H40: Bookcases | I40: Throughout Bookcases | J40: 2551.77 | K40: 5 | L40: 0 | M40: -380.82
A41: ORD-10040 | B41: 46089 | C41: 46095 | D41: Brian Gallagher | E41: Home Office | F41: West | G41: Furniture | H41: Chairs | I41: According Chairs | J41: 3867.04 | K41: 5 | L41: 0.05 | M41: 803.1
A42: ORD-10041 | B42: 45846 | C42: 45848 | D42: Melissa Burgess | E42: Corporate | F42: South | G42: Office Supplies | H42: Binders | I42: Three Binders | J42: 422.46 | K42: 3 | L42: 0.2 | M42: -76.12
A43: ORD-10042 | B43: 46158 | C43: 46159 | D43: Jenna Hill | E43: Consumer | F43: North | G43: Technology | H43: Phones | I43: Employee Phones | J43: 1575.88 | K43: 1 | L43: 0.1 | M43: -133.1
A44: ORD-10043 | B44: 46057 | C44: 46064 | D44: Steven Moody | E44: Consumer | F44: West | G44: Technology | H44: Laptops | I44: Writer Laptops | J44: 4870.49 | K44: 3 | L44: 0.05 | M44: 1341.98
A45: ORD-10044 | B45: 45839 | C45: 45845 | D45: Donald Prince | E45: Consumer | F45: East | G45: Furniture | H45: Chairs | I45: Development Chairs | J45: 3922.81 | K45: 7 | M45: 1079.7
A46: ORD-10045 | B46: 45549 | C46: 45551 | D46: Michael Robinson | E46: Corporate | F46: East | G46: Furniture | H46: Bookcases | I46: These Bookcases | J46: 1943.58 | K46: 1 | L46: 0.15 | M46: -150.94
A47: ORD-10046 | B47: 45230 | C47: 45234 | D47: Christina Cooper | E47: Consumer | F47: East | G47: Technology | H47: Phones | I47: Live Phones | J47: 167.14 | K47: 4 | L47: 0.15 | M47: -3.25
A48: ORD-10047 | B48: 45757 | C48: 45766 | D48: David Anderson | E48: Consumer | F48: East | G48: Technology | H48: Laptops | I48: Interesting Laptops | J48: 2028.41 | K48: 9 | L48: 0.1 | M48: 642.15
A49: ORD-10048 | B49: 45409 | C49: 45414 | D49: Ann Conner | E49: Corporate | F49: West | G49: Furniture | H49: Bookcases | I49: Effort Bookcases | J49: 239.37 | K49: 10 | L49: 0.15 | M49: -2.36
A50: ORD-10049 | B50: 46007 | C50: 46009 | D50: David Morgan | E50: Home Office | F50: West | G50: Office Supplies | H50: Storage | I50: Man Storage | J50: 1956.72 | K50: 10 | L50: 0.05 | M50: -117.21
A51: ORD-10050 | B51: 45715 | C51: 45724 | D51: Andrea Carrillo | E51: Home Office | F51: East | G51: Furniture | H51: Bookcases | I51: Chair Bookcases | J51: 3449.94 | K51: 4 | L51: 0.1 | M51: 128.38
A52: ORD-10051 | B52: 45385 | C52: 45387 | D52: Laura James | E52: Corporate | F52: East | G52: Office Supplies | H52: Paper | I52: News Paper | J52: 3612.78 | K52: 5 | L52: 0.2 | M52: -108
A53: ORD-10052 | B53: 45830 | C53: 45835 | D53: Charles Torres | E53: Corporate | F53: South | G53: Technology | H53: Laptops | I53: Open Laptops | J53: 2794.34 | K53: 4 | L53: 0.15 | M53: 463.05
A54: ORD-10053 | B54: 24-01-2024 | C54: 45320 | D54: Alexander Taylor | E54: Corporate | F54: East | G54: Office Supplies | H54: Storage | I54: History Storage | J54: 2060.07 | K54: 1 | L54: 0.1 | M54: -86.93
A55: ORD-10054 | B55: 45939 | C55: 45947 | D55: Walter Lindsey | E55: Home Office | F55: South | G55: Technology | H55: Accessories | I55: Stay Accessories | J55: 3394.35 | K55: 9 | L55: 0.15 | M55: 802.95
A56: ORD-10055 | B56: 45720 | C56: 45725 | D56: Jennifer Downs | E56: Consumer | F56: East | G56: Office Supplies | H56: Binders | I56: Support Binders | J56: 2601.49 | K56: 10 | L56: 0.1 | M56: -386.68
A57: ORD-10056 | B57: 45424 | C57: 45427 | D57: Tara Ferguson | E57: Consumer | F57: West | G57: Furniture | H57: Chairs | I57: Just Chairs | J57: 170.91 | K57: 4 | L57: 0.15 | M57: 23.28
A58: ORD-10057 | B58: 45773 | C58: 45783 | D58: Brittany Woodward | E58: Consumer | F58: North | G58: Technology | H58: Laptops | I58: Laugh Laptops | J58: 1012.45 | K58: 7 | L58: 0.15 | M58: 20.06
A59: ORD-10058 | B59: 45366 | C59: 45370 | D59: Johnathan Logan | E59: Consumer | F59: North | G59: Furniture | H59: Tables | I59: Baby Tables | J59: 920.64 | K59: 9 | L59: 0.15 | M59: -158.7
A60: ORD-10059 | B60: 45364 | C60: 45372 | D60: Maria Walker | E60: Corporate | F60: West | G60: Technology | H60: Phones | I60: Memory Phones | J60: 3354.51 | K60: 9 | L60: 0.2 | M60: -85.49
A61: ORD-10060 | B61: 45861 | C61: 45864 | D61: Robert Willis | E61: Consumer | F61: East | G61: Office Supplies | H61: Paper | I61: Different Paper | J61: 3731.09 | K61: 8 | L61: 0.15 | M61: -214.33
A62: ORD-10061 | B62: 45691 | C62: 45695 | D62: Wanda Byrd | E62: Corporate | F62: East | G62: Office Supplies | H62: Paper | I62: Fact Paper | J62: 1409.26 | K62: 2 | M62: -60.39
A63: ORD-10062 | B63: 45190 | C63: 45192 | D63: John Potts | E63: Home Office | F63: South | G63: Technology | H63: Laptops | I63: Shake Laptops | J63: 734.95 | K63: 4 | L63: 0.15 | M63: 133.52
A64: ORD-10063 | B64: 45390 | C64: 45397 | D64: Monica Kelley | E64: Corporate | F64: West | G64: Furniture | H64: Tables | I64: Power Tables | J64: 1687.86 | K64: 8 | L64: 0.15 | M64: -279.77
A65: ORD-10064 | B65: 45373 | C65: 45374 | D65: Justin Farrell | E65: Corporate | F65: East | G65: Office Supplies | H65: Storage | I65: These Storage | J65: 4290.82 | K65: 10 | L65: 0.15 | M65: 267.48
A66: ORD-10065 | B66: 46122 | C66: 46131 | D66: Joseph Sanchez | E66: Corporate | F66: South | G66: Technology | H66: Accessories | I66: Still Accessories | J66: 3750.2 | K66: 9 | L66: 0.2 | M66: 1101.79
A67: ORD-10066 | B67: 45482 | C67: 45490 | D67: Kenneth Dunn | E67: Corporate | F67: South | G67: Technology | H67: Accessories | I67: Interest Accessories | J67: 193.67 | K67: 6 | M67: 33.61
A68: ORD-10067 | B68: 45134 | C68: 45144 | D68: Christina Henry | E68: Consumer | F68: North | G68: Technology | H68: Phones | I68: Moment Phones | J68: 2693.91 | K68: 7 | L68: 0.2 | M68: 297.45
A69: ORD-10068 | B69: 46123 | C69: 46126 | D69: Jessica Smith | E69: Corporate | F69: South | G69: Office Supplies | H69: Paper | I69: Write Paper | J69: 4340.91 | K69: 3 | L69: 0 | M69: -247.06
A70: ORD-10069 | B70: 45148 | C70: 45154 | D70: Daniel Williamson | E70: Corporate | F70: East | G70: Technology | H70: Accessories | I70: By Accessories | J70: 3818.09 | K70: 7 | L70: 0.1 | M70: 815.56
A71: ORD-10070 | B71: 45993 | C71: 45994 | D71: Sean Miranda | E71: Consumer | F71: North | G71: Furniture | H71: Tables | I71: Number Tables | J71: 3757.67 | K71: 1 | L71: 0.1 | M71: -288.13
A72: ORD-10071 | B72: 45264 | C72: 45268 | D72: Kelly Yoder | E72: Corporate | F72: North | G72: Furniture | H72: Chairs | I72: Next Chairs | J72: 4204.18 | K72: 10 | L72: 0.05 | M72: -289.25
A73: ORD-10072 | B73: 45102 | C73: 45110 | D73: Cristian Graham | E73: Home Office | F73: North | G73: Office Supplies | H73: Binders | I73: Back Binders | J73: 3512.35 | K73: 6 | L73: 0.05 | M73: 467.99
A74: ORD-10073 | B74: 45081 | C74: 45083 | D74: Patricia Rojas | E74: Corporate | F74: West | G74: Furniture | H74: Tables | I74: Despite Tables | J74: 2914.49 | K74: 5 | L74: 0.2 | M74: 502.87
A75: ORD-10074 | B75: 45992 | C75: 45994 | D75: Elizabeth Martin | E75: Corporate | F75: North | G75: Office Supplies | H75: Binders | I75: Generation Binders | J75: 2980.88 | K75: 4 | L75: 0 | M75: 546.86
A76: ORD-10075 | B76: 45071 | C76: 45077 | D76: Mr. Nicholas Fischer III | E76: Corporate | F76: North | G76: Office Supplies | H76: Binders | I76: Whose Binders | J76: 2687.09 | K76: 6 | L76: 0 | M76: 210.34
A77: ORD-10076 | B77: 45370 | C77: 45372 | D77: Michael Whitney | E77: Corporate | F77: South | G77: Technology | H77: Accessories | I77: Give Accessories | J77: 2195.94 | K77: 6 | M77: 637.63
A78: ORD-10077 | B78: 17-09-2023 | C78: 45195 | D78: William Gonzalez | E78: Home Office | F78: West | G78: Technology | H78: Phones | I78: Type Phones | J78: 4829.09 | K78: 5 | L78: 0.2 | M78: 1180.76
A79: ORD-10078 | B79: 45614 | C79: 45624 | D79: Gabriel Daniels | E79: Corporate | F79: South | G79: Technology | H79: Accessories | I79: Theory Accessories | J79: 1378.56 | K79: 4 | L79: 0 | M79: -64.23
A80: ORD-10079 | B80: 45551 | C80: 45561 | D80: Monica Price | E80: Corporate | F80: South | G80: Technology | H80: Laptops | I80: While Laptops | J80: 3357.53 | K80: 6 | L80: 0 | M80: 241.3
A81: ORD-10080 | B81: 45485 | C81: 45491 | D81: Christine Wood | E81: Home Office | F81: East | G81: Technology | H81: Phones | I81: Wrong Phones | J81: 3999.27 | K81: 6 | L81: 0.1 | M81: 1136.5
A82: ORD-10081 | B82: 45493 | C82: 45502 | D82: Christopher Becker | E82: Corporate | F82: South | G82: Office Supplies | H82: Binders | I82: It Binders | J82: 4742.91 | K82: 2 | L82: 0.05 | M82: 929.81
A83: ORD-10082 | B83: 45411 | C83: 45419 | D83: Brandon Barker | E83: Corporate | F83: South | G83: Office Supplies | H83: Paper | I83: Everybody Paper | J83: 2268.46 | K83: 1 | L83: 0 | M83: -86.59
A84: ORD-10083 | B84: 45827 | C84: 45837 | D84: Teresa Velazquez | E84: Home Office | F84: East | G84: Technology | H84: Laptops | I84: Power Laptops | J84: 1876.65 | K84: 9 | L84: 0.2 | M84: -20.52
A85: ORD-10084 | B85: 45676 | C85: 45684 | D85: Kristen Payne | E85: Consumer | F85: East | G85: Technology | H85: Laptops | I85: Small Laptops | J85: 1391.04 | K85: 5 | L85: 0.05 | M85: -185.9
A86: ORD-10085 | B86: 45138 | C86: 45147 | D86: Brittany Bradley | E86: Corporate | F86: East | G86: Furniture | H86: Bookcases | I86: Adult Bookcases | J86: 4756.84 | K86: 3 | L86: 0.05 | M86: -385.25
A87: ORD-10086 | B87: 45760 | C87: 45769 | D87: Christy Harris | E87: Corporate | F87: South | G87: Office Supplies | H87: Storage | I87: Fear Storage | J87: 3004.11 | K87: 2 | L87: 0.05 | M87: -111.35
A88: ORD-10087 | B88: 45796 | C88: 45805 | D88: Jeremy Hood | E88: Home Office | F88: South | G88: Technology | H88: Phones | I88: Drug Phones | J88: 676.59 | K88: 1 | L88: 0 | M88: 70.6
A89: ORD-10088 | B89: 46021 | C89: 46023 | D89: Daniel Clark | E89: Corporate | F89: East | G89: Office Supplies | H89: Paper | I89: Since Paper | J89: 4369.96 | K89: 10 | L89: 0.1 | M89: 254.19
A90: ORD-10089 | B90: 45878 | C90: 45883 | D90: Jill Ayers | E90: Corporate | F90: West | G90: Furniture | H90: Chairs | I90: Third Chairs | J90: 4708.26 | K90: 8 | L90: 0 | M90: 1187.25
... A96: ORD-10095 | B96: 45871 | C96: 45879 | D96: Amanda Watkins | E96: Home Office | F96: South | G96: Office Supplies | H96: Paper | I96: What Paper | J96: 402.34 | K96: 4 | L96: 0.1 | M96: 93.87
A97: ORD-10096 | B97: 17-08-2024 | C97: 45530 | D97: Kimberly Wood | E97: Consumer | F97: North | G97: Technology | H97: Phones | I97: Admit Phones | J97: 1162.81 | K97: 3 | L97: 0.1 | M97: 296.11
A98: ORD-10097 | B98: 45298 | C98: 45308 | D98: Eric Collins | E98: Corporate | F98: East | G98: Furniture | H98: Tables | I98: Year Tables | J98: 3757.34 | K98: 10 | L98: 0.1 | M98: 156.06
A99: ORD-10098 | B99: 45299 | C99: 45304 | E99: Consumer | F99: West | G99: Office Supplies | H99: Paper | I99: Chance Paper | J99: 2527.34 | K99: 8 | L99: 0.15 | M99: -393.65
A100: ORD-10099 | B100: 45936 | C100: 45946 | D100: Yolanda Burke | E100: Home Office | F100: North | G100: Office Supplies | H100: Paper | I100: Fall Paper | J100: 1289.32 | K100: 2 | L100: 0.05 | M100: 424.25
A101: ORD-10100 | B101: 46108 | C101: 46118 | D101: Sara Miller | E101: Corporate | F101: East | G101: Office Supplies | H101: Paper | I101: Song Paper | J101: 249.15 | K101: 3 | L101: 0.15 | M101: 21.28
A102: ORD-10101 | B102: 45449 | C102: 45456 | D102: Jacqueline Hernandez | E102: Corporate | F102: East | G102: Furniture | H102: Bookcases | I102: End Bookcases | J102: 3192.18 | K102: 8 | L102: 0 | M102: 186.76
A103: ORD-10102 | B103: 45625 | C103: 45627 | D103: Frederick Norris | E103: Corporate | F103: West | G103: Technology | H103: Laptops | I103: Role Laptops | J103: 4295.78 | K103: 6 | L103: 0.15 | M103: 779.77
A104: ORD-10103 | B104: 45636 | C104: 45644 | D104: Richard Day | E104: Corporate | F104: North | G104: Office Supplies | H104: Binders | I104: Money Binders | J104: 485.9 | K104: 5 | L104: 0.1 | M104: -66.2
A105: ORD-10104 | B105: 46150 | C105: 46158 | D105: Michelle Ryan | E105: Corporate | F105: West | G105: Office Supplies | H105: Storage | I105: Somebody Storage | J105: 2095.58 | K105: 4 | L105: 0.2 | M105: -2.14
A106: ORD-10105 | B106: 45213 | C106: 45218 | D106: Robert Rice | E106: Corporate | G106: Furniture | H106: Chairs | I106: Manager Chairs | J106: 2768.64 | K106: 5 | L106: 0.15 | M106: 787.58
A107: ORD-10106 | B107: 45551 | C107: 45561 | D107: Samantha Hernandez PhD | E107: Home Office | F107: West | G107: Furniture | H107: Bookcases | I107: Something Bookcases | J107: 4006.6 | K107: 3 | L107: 0.1 | M107: 412.53
...

Sheet data cleaning
A1: Order ID | B1: Order Date | C1: Ship Date | D1: Customer Name3 | E1: Customer Name2 | F1: Segment | G1: Segment2 | H1: Region | I1: Region2 | J1: Category | K1: Category2 | L1: Sub-Category | M1: Sub-Category2 | N1: Product Name | O1: Product Name3 | P1: Product Name2 | Q1: Sales | R1: Quantity | S1: Discount | T1: Profit
A2: ORD-10001 | B2: 45177 | C2: 45178 | D2: =TRIM('data cleaning'!$E2) -> Traci Sanchez | E2: Traci Sanchez | F2: =TRIM('data cleaning'!$G2) -> Consumer | G2: Consumer | H2: =TRIM('data cleaning'!$I2) -> North | I2: North | J2: =TRIM('data cleaning'!$K2) -> Office Supplies | K2: Office Supplies | L2: =TRIM('data cleaning'!$M2) -> Binders | M2: Binders | N2: =PROPER('data cleaning'!$O2) -> Happy Binders | O2: =TRIM('data cleaning'!$P2) -> Happy Binders | P2: Happy Binders | Q2: 3720.67 | R2: 4 | S2: 0.05 | T2: -458.59
A3: ORD-10002 | B3: 46086 | C3: 46087 | D3: =TRIM('data cleaning'!$E3) -> Norman Jordan | E3: Norman Jordan | F3: =TRIM('data cleaning'!$G3) -> Consumer | G3: Consumer | H3: =TRIM('data cleaning'!$I3) -> South | I3: South | J3: =TRIM('data cleaning'!$K3) -> Office Supplies | K3: Office Supplies | L3: =TRIM('data cleaning'!$M3) -> Paper | M3: Paper | N3: =PROPER('data cleaning'!$O3) -> Fight Paper | O3: =TRIM('data cleaning'!$P3) -> Fight Paper | P3: Fight Paper | Q3: 197.5 | R3: 4 | S3: 0.05 | T3: 15.39
A4: ORD-10003 | B4: 45235 | C4: 45244 | D4: =TRIM('data cleaning'!$E4) -> Thomas Scott | E4: Thomas Scott | F4: =TRIM('data cleaning'!$G4) -> Consumer | G4: Consumer | H4: =TRIM('data cleaning'!$I4) -> South | I4: South | J4: =TRIM('data cleaning'!$K4) -> Office Supplies | K4: Office Supplies | L4: =TRIM('data cleaning'!$M4) -> Storage | M4: Storage | N4: =PROPER('data cleaning'!$O4) -> Process Storage | O4: =TRIM('data cleaning'!$P4) -> Process Storage | P4: Process Storage | Q4: 2126.62 | R4: 8 | S4: 0.2 | T4: -99.94
A5: ORD-10004 | B5: 45523 | C5: 45529 | D5: =TRIM('data cleaning'!$E5) -> Samuel Diaz | E5: Samuel Diaz | F5: =TRIM('data cleaning'!$G5) -> Corporate | G5: Corporate | H5: =TRIM('data cleaning'!$I5) -> North | I5: North | J5: =TRIM('data cleaning'!$K5) -> Office Supplies | K5: Office Supplies | L5: =TRIM('data cleaning'!$M5) -> Paper | M5: Paper | N5: =PROPER('data cleaning'!$O5) -> Prepare Paper | O5: =TRIM('data cleaning'!$P5) -> Prepare Paper | P5: Prepare Paper | Q5: 1425.46 | R5: 4 | S5: 0.1 | T5: -204.96
A6: ORD-10005 | B6: 45860 | C6: 45870 | D6: =TRIM('data cleaning'!$E6) -> Tiffany Ruiz | E6: Tiffany Ruiz | F6: =TRIM('data cleaning'!$G6) -> Consumer | G6: Consumer | H6: =TRIM('data cleaning'!$I6) -> West | I6: West | J6: =TRIM('data cleaning'!$K6) -> Technology | K6: Technology | L6: =TRIM('data cleaning'!$M6) -> Accessories | M6: Accessories | N6: =PROPER('data cleaning'!$O6) -> Coach Accessories | O6: =TRIM('data cleaning'!$P6) -> Coach Accessories | P6: Coach Accessories | Q6: 1359.38 | R6: 1 | T6: 71.62
A7: ORD-10006 | B7: 45335 | C7: 45340 | D7: =TRIM('data cleaning'!$E7) -> Stephanie Rodriguez | E7: Stephanie Rodriguez | F7: =TRIM('data cleaning'!$G7) -> Home Office | G7: Home Office | H7: =TRIM('data cleaning'!$I7) -> North | I7: North | J7: =TRIM('data cleaning'!$K7) -> Furniture | K7: Furniture | L7: =TRIM('data cleaning'!$M7) -> Bookcases | M7: Bookcases | N7: =PROPER('data cleaning'!$O7) -> Task Bookcases | O7: =TRIM('data cleaning'!$P7) -> Task Bookcases | P7: Task Bookcases | Q7: 4155.55 | R7: 10 | S7: 0.1 | T7: 488.46
A8: ORD-10007 | B8: 46018 | C8: 46022 | D8: =TRIM('data cleaning'!$E8) -> Barbara Mora | E8: Barbara Mora | F8: =TRIM('data cleaning'!$G8) -> Corporate | G8: Corporate | H8: =TRIM('data cleaning'!$I8) -> East | I8: East | J8: =TRIM('data cleaning'!$K8) -> Furniture | K8: Furniture | L8: =TRIM('data cleaning'!$M8) -> Bookcases | M8: Bookcases | N8: =PROPER('data cleaning'!$O8) -> Available Bookcases | O8: =TRIM('data cleaning'!$P8) -> Available Bookcases | P8: Available Bookcases | Q8: 3876.69 | R8: 2 | S8: 0.05 | T8: 1072.16
A9: ORD-10008 | B9: 45288 | C9: 45294 | D9: =TRIM('data cleaning'!$E9) -> Gloria Brown | E9: Gloria Brown | F9: =TRIM('data cleaning'!$G9) -> Home Office | G9: Home Office | H9: =TRIM('data cleaning'!$I9) -> North | I9: North | J9: =TRIM('data cleaning'!$K9) -> Technology | K9: Technology | L9: =TRIM('data cleaning'!$M9) -> Laptops | M9: Laptops | N9: =PROPER('data cleaning'!$O9) -> Beautiful Laptops | O9: =TRIM('data cleaning'!$P9) -> Beautiful Laptops | P9: Beautiful Laptops | Q9: 855.14 | R9: 6 | S9: 0.05 | T9: 144.17
A10: ORD-10009 | B10: 45374 | C10: 45377 | D10: =TRIM('data cleaning'!$E10) -> Stephen Adkins | E10: Stephen Adkins | F10: =TRIM('data cleaning'!$G10) -> Corporate | G10: Corporate | H10: =TRIM('data cleaning'!$I10) -> South | I10: South | J10: =TRIM('data cleaning'!$K10) -> Office Supplies | K10: Office Supplies | L10: =TRIM('data cleaning'!$M10) -> Storage | M10: Storage | N10: =PROPER('data cleaning'!$O10) -> Purpose Storage | O10: =TRIM('data cleaning'!$P10) -> Purpose Storage | P10: Purpose Storage | Q10: 2693.99 | R10: 4 | S10: 0.05 | T10: 146.13
A11: ORD-10010 | B11: 46080 | C11: 46081 | D11: =TRIM('data cleaning'!$E11) -> Rachel Mathews | E11: Rachel Mathews | F11: =TRIM('data cleaning'!$G11) -> Consumer | G11: Consumer | H11: =TRIM('data cleaning'!$I11) -> South | I11: South | J11: =TRIM('data cleaning'!$K11) -> Office Supplies | K11: Office Supplies | L11: =TRIM('data cleaning'!$M11) -> Paper | M11: Paper | N11: =PROPER('data cleaning'!$O11) -> Last Paper | O11: =TRIM('data cleaning'!$P11) -> Last Paper | P11: Last Paper | Q11: 1183.79 | R11: 1 | S11: 0.1 | T11: 24.43
A12: ORD-10011 | B12: 45524 | C12: 45530 | D12: =TRIM('data cleaning'!$E12) -> Jacqueline Johnson | E12: Jacqueline Johnson | F12: =TRIM('data cleaning'!$G12) -> Home Office | G12: Home Office | H12: =TRIM('data cleaning'!$I12) -> West | I12: West | J12: =TRIM('data cleaning'!$K12) -> Office Supplies | K12: Office Supplies | L12: =TRIM('data cleaning'!$M12) -> Storage | M12: Storage | N12: =PROPER('data cleaning'!$O12) -> Prepare Storage | O12: =TRIM('data cleaning'!$P12) -> Prepare Storage | P12: Prepare Storage | Q12: 1102.5 | R12: 8 | S12: 0.15 | T12: 315.95
A13: ORD-10012 | B13: 45574 | C13: 45577 | D13: =TRIM('data cleaning'!$E13) -> Kevin Anderson | E13: Kevin Anderson | F13: =TRIM('data cleaning'!$G13) -> Home Office | G13: Home Office | H13: =TRIM('data cleaning'!$I13) -> West | I13: West | J13: =TRIM('data cleaning'!$K13) -> Furniture | K13: Furniture | L13: =TRIM('data cleaning'!$M13) -> Tables | M13: Tables | N13: =PROPER('data cleaning'!$O13) -> Live Tables | O13: =TRIM('data cleaning'!$P13) -> Live Tables | P13: Live Tables | Q13: 1270.81 | R13: 9 | S13: 0.2 | T13: -70.52
A14: ORD-10013 | B14: 45524 | C14: 45530 | D14: =TRIM('data cleaning'!$E14) -> Kenneth Sullivan | E14: Kenneth Sullivan | F14: =TRIM('data cleaning'!$G14) -> Consumer | G14: Consumer | H14: =TRIM('data cleaning'!$I14) -> North | I14: North | J14: =TRIM('data cleaning'!$K14) -> Office Supplies | K14: Office Supplies | L14: =TRIM('data cleaning'!$M14) -> Paper | M14: Paper | N14: =PROPER('data cleaning'!$O14) -> Example Paper | O14: =TRIM('data cleaning'!$P14) -> Example Paper | P14: Example Paper | Q14: 1135.64 | R14: 3 | S14: 0.2 | T14: 81.12
A15: ORD-10014 | B15: 45338 | C15: 45341 | D15: =TRIM('data cleaning'!$E15) -> John Bates | E15: John Bates | F15: =TRIM('data cleaning'!$G15) -> Corporate | G15: Corporate | H15: =TRIM('data cleaning'!$I15) -> West | I15: West | J15: =TRIM('data cleaning'!$K15) -> Furniture | K15: Furniture | L15: =TRIM('data cleaning'!$M15) -> Bookcases | M15: Bookcases | N15: =PROPER('data cleaning'!$O15) -> Individual Bookcases | O15: =TRIM('data cleaning'!$P15) -> Individual Bookcases | P15: Individual Bookcases | Q15: 3970.79 | R15: 7 | S15: 0.2 | T15: -655.42
A16: ORD-10015 | B16: 45214 | C16: 45223 | D16: =TRIM('data cleaning'!$E16) -> Patrick Horn | E16: Patrick Horn | F16: =TRIM('data cleaning'!$G16) -> Home Office | G16: Home Office | H16: =TRIM('data cleaning'!$I16) -> East | I16: East | J16: =TRIM('data cleaning'!$K16) -> Office Supplies | K16: Office Supplies | L16: =TRIM('data cleaning'!$M16) -> Paper | M16: Paper | N16: =PROPER('data cleaning'!$O16) -> Tough Paper | O16: =TRIM('data cleaning'!$P16) -> Tough Paper | P16: Tough Paper | Q16: 4310.86 | R16: 1 | T16: 846.64
A17: ORD-10016 | B17: 45297 | C17: 45299 | D17: =TRIM('data cleaning'!$E17) -> Danny Clark | E17: Danny Clark | F17: =TRIM('data cleaning'!$G17) -> Home Office | G17: Home Office | H17: =TRIM('data cleaning'!$I17) -> East | I17: East | J17: =TRIM('data cleaning'!$K17) -> Office Supplies | K17: Office Supplies | L17: =TRIM('data cleaning'!$M17) -> Paper | M17: Paper | N17: =PROPER('data cleaning'!$O17) -> Cover Paper | O17: =TRIM('data cleaning'!$P17) -> Cover Paper | P17: Cover Paper | Q17: 1502.83 | R17: 3 | S17: 0.15 | T17: -297.88
A18: ORD-10017 | B18: 45233 | C18: 45242 | D18: =TRIM('data cleaning'!$E18) -> Thomas Olson | E18: Thomas Olson | F18: =TRIM('data cleaning'!$G18) -> Consumer | G18: Consumer | H18: =TRIM('data cleaning'!$I18) -> South | I18: South | J18: =TRIM('data cleaning'!$K18) -> Office Supplies | K18: Office Supplies | L18: =TRIM('data cleaning'!$M18) -> Binders | M18: Binders | N18: =PROPER('data cleaning'!$O18) -> Thousand Binders | O18: =TRIM('data cleaning'!$P18) -> Thousand Binders | P18: Thousand Binders | Q18: 4567.51 | R18: 5 | T18: 361.81
A19: ORD-10018 | B19: 45669 | C19: 45678 | D19: =TRIM('data cleaning'!$E19) -> Jeffrey Levy | E19: Jeffrey Levy | F19: =TRIM('data cleaning'!$G19) -> Corporate | G19: Corporate | H19: =TRIM('data cleaning'!$I19) -> North | I19: North | J19: =TRIM('data cleaning'!$K19) -> Technology | K19: Technology | L19: =TRIM('data cleaning'!$M19) -> Phones | M19: Phones | N19: =PROPER('data cleaning'!$O19) -> Ahead Phones | O19: =TRIM('data cleaning'!$P19) -> Ahead Phones | P19: Ahead Phones | Q19: 4769.82 | R19: 9 | S19: 0 | T19: 617.31
A20: ORD-10019 | B20: 45262 | C20: 45267 | D20: =TRIM('data cleaning'!$E20) -> James Hamilton | E20: James Hamilton | F20: =TRIM('data cleaning'!$G20) -> Consumer | G20: Consumer | H20: =TRIM('data cleaning'!$I20) -> West | I20: West | J20: =TRIM('data cleaning'!$K20) -> Furniture | K20: Furniture | L20: =TRIM('data cleaning'!$M20) -> Tables | M20: Tables | N20: =PROPER('data cleaning'!$O20) -> Build Tables | O20: =TRIM('data cleaning'!$P20) -> Build Tables | P20: Build Tables | Q20: 1235.29 | R20: 4 | S20: 0.2 | T20: 396.31
A21: ORD-10020 | B21: 45662 | C21: 45665 | D21: =TRIM('data cleaning'!$E21) -> Joshua Smith | E21: Joshua Smith | F21: =TRIM('data cleaning'!$G21) -> Home Office | G21: Home Office | H21: =TRIM('data cleaning'!$I21) -> West | I21: West | J21: =TRIM('data cleaning'!$K21) -> Furniture | K21: Furniture | L21: =TRIM('data cleaning'!$M21) -> Bookcases | M21: Bookcases | N21: =PROPER('data cleaning'!$O21) -> Cell Bookcases | O21: =TRIM('data cleaning'!$P21) -> Cell Bookcases | P21: Cell Bookcases | Q21: 685.54 | R21: 8 | S21: 0.2 | T21: -74.85
A22: ORD-10021 | B22: 46154 | C22: 46158 | D22: =TRIM('data cleaning'!$E22) -> Lorraine Ruiz | E22: Lorraine Ruiz | F22: =TRIM('data cleaning'!$G22) -> Corporate | G22: Corporate | H22: =TRIM('data cleaning'!$I22) -> West | I22: West | J22: =TRIM('data cleaning'!$K22) -> Furniture | K22: Furniture | L22: =TRIM('data cleaning'!$M22) -> Bookcases | M22: Bookcases | N22: =PROPER('data cleaning'!$O22) -> Suddenly Bookcases | O22: =TRIM('data cleaning'!$P22) -> Suddenly Bookcases | P22: Suddenly Bookcases | Q22: 3579.1 | R22: 7 | T22: 563.47
A23: ORD-10022 | B23: 45989 | C23: 45993 | D23: =TRIM('data cleaning'!$E23) -> Terri Miller | E23: Terri Miller | F23: =TRIM('data cleaning'!$G23) -> Home Office | G23: Home Office | H23: =TRIM('data cleaning'!$I23) -> South | I23: South | J23: =TRIM('data cleaning'!$K23) -> Furniture | K23: Furniture | L23: =TRIM('data cleaning'!$M23) -> Chairs | M23: Chairs | N23: =PROPER('data cleaning'!$O23) -> Forget Chairs | O23: =TRIM('data cleaning'!$P23) -> Forget Chairs | P23: Forget Chairs | Q23: 366.93 | R23: 1 | S23: 0.2 | T23: 38.4
A24: ORD-10023 | B24: 45383 | C24: 45384 | D24: =TRIM('data cleaning'!$E24) -> Stacey Lewis | E24: Stacey Lewis | F24: =TRIM('data cleaning'!$G24) -> Consumer | G24: Consumer | H24: =TRIM('data cleaning'!$I24) -> East | I24: East | J24: =TRIM('data cleaning'!$K24) -> Furniture | K24: Furniture | L24: =TRIM('data cleaning'!$M24) -> Chairs | M24: Chairs | N24: =PROPER('data cleaning'!$O24) -> Than Chairs | O24: =TRIM('data cleaning'!$P24) -> Than Chairs | P24: Than Chairs | Q24: 1183.26 | R24: 1 | S24: 0.1 | T24: -190.54
A25: ORD-10024 | B25: 45796 | C25: 45800 | D25: =TRIM('data cleaning'!$E25) -> Amanda Roberts | E25: Amanda Roberts | F25: =TRIM('data cleaning'!$G25) -> Corporate | G25: Corporate | H25: =TRIM('data cleaning'!$I25) -> West | I25: West | J25: =TRIM('data cleaning'!$K25) -> Office Supplies | K25: Office Supplies | L25: =TRIM('data cleaning'!$M25) -> Paper | M25: Paper | N25: =PROPER('data cleaning'!$O25) -> Culture Paper | O25: =TRIM('data cleaning'!$P25) -> Culture Paper | P25: Culture Paper | Q25: 2719.21 | R25: 10 | S25: 0.2 | T25: 163.07
A26: ORD-10025 | B26: 45564 | C26: 45566 | D26: =TRIM('data cleaning'!$E26) -> William Fernandez | E26: William Fernandez | F26: =TRIM('data cleaning'!$G26) -> Home Office | G26: Home Office | H26: =TRIM('data cleaning'!$I26) -> North | I26: North | J26: =TRIM('data cleaning'!$K26) -> Furniture | K26: Furniture | L26: =TRIM('data cleaning'!$M26) -> Chairs | M26: Chairs | N26: =PROPER('data cleaning'!$O26) -> Cultural Chairs | O26: =TRIM('data cleaning'!$P26) -> Cultural Chairs | P26: Cultural Chairs | Q26: 3311.96 | R26: 6 | S26: 0.15 | T26: 86.46
A27: ORD-10026 | B27: 45647 | C27: 45649 | D27: =TRIM('data cleaning'!$E27) -> Nicholas Taylor | E27: Nicholas Taylor | F27: =TRIM('data cleaning'!$G27) -> Consumer | G27: Consumer | H27: =TRIM('data cleaning'!$I27) -> West | I27: West | J27: =TRIM('data cleaning'!$K27) -> Office Supplies | K27: Office Supplies | L27: =TRIM('data cleaning'!$M27) -> Storage | M27: Storage | N27: =PROPER('data cleaning'!$O27) -> Make Storage | O27: =TRIM('data cleaning'!$P27) -> Make Storage | P27: Make Storage | Q27: 350.03 | R27: 6 | S27: 0 | T27: -22.14
A28: ORD-10027 | B28: 45441 | C28: 45444 | D28: =TRIM('data cleaning'!$E28) -> Amanda Roy | E28: Amanda Roy | F28: =TRIM('data cleaning'!$G28) -> Home Office | G28: Home Office | H28: =TRIM('data cleaning'!$I28) -> North | I28: North | J28: =TRIM('data cleaning'!$K28) -> Furniture | K28: Furniture | L28: =TRIM('data cleaning'!$M28) -> Tables | M28: Tables | N28: =PROPER('data cleaning'!$O28) -> His Tables | O28: =TRIM('data cleaning'!$P28) -> His Tables | P28: His Tables | Q28: 1428.8 | R28: 4 | S28: 0 | T28: 62.47
A29: ORD-10028 | B29: 45683 | C29: 45692 | D29: =TRIM('data cleaning'!$E29) -> Charles Moore | E29: Charles Moore | F29: =TRIM('data cleaning'!$G29) -> Corporate | G29: Corporate | H29: =TRIM('data cleaning'!$I29) -> West | I29: West | J29: =TRIM('data cleaning'!$K29) -> Furniture | K29: Furniture | L29: =TRIM('data cleaning'!$M29) -> Bookcases | M29: Bookcases | N29: =PROPER('data cleaning'!$O29) -> Yeah Bookcases | O29: =TRIM('data cleaning'!$P29) -> Yeah Bookcases | P29: Yeah Bookcases | Q29: 4188.34 | R29: 2 | S29: 0.05 | T29: -454.56
A30: ORD-10029 | B30: 45352 | C30: 45353 | D30: =TRIM('data cleaning'!$E30) -> Linda Wells | E30: Linda Wells | F30: =TRIM('data cleaning'!$G30) -> Corporate | G30: Corporate | H30: =TRIM('data cleaning'!$I30) -> East | I30: East | J30: =TRIM('data cleaning'!$K30) -> Furniture | K30: Furniture | L30: =TRIM('data cleaning'!$M30) -> Tables | M30: Tables | N30: =PROPER('data cleaning'!$O30) -> Important Tables | O30: =TRIM('data cleaning'!$P30) -> Important Tables | P30: Important Tables | Q30: 864.95 | R30: 1 | S30: 0.15 | T30: -46.83
A31: ORD-10030 | B31: 45088 | C31: 45097 | D31: =TRIM('data cleaning'!$E31) -> Daniel King | E31: Daniel King | F31: =TRIM('data cleaning'!$G31) -> Consumer | G31: Consumer | H31: =TRIM('data cleaning'!$I31) -> North | I31: North | J31: =TRIM('data cleaning'!$K31) -> Technology | K31: Technology | L31: =TRIM('data cleaning'!$M31) -> Laptops | M31: Laptops | N31: =PROPER('data cleaning'!$O31) -> Themselves Laptops | O31: =TRIM('data cleaning'!$P31) -> Themselves Laptops | P31: Themselves Laptops | Q31: 3326.26 | R31: 8 | S31: 0.05 | T31: -317.84
A32: ORD-10031 | B32: 46145 | C32: 46154 | D32: =TRIM('data cleaning'!$E32) -> Ricardo Ramirez | E32: Ricardo Ramirez | F32: =TRIM('data cleaning'!$G32) -> Corporate | G32: Corporate | H32: =TRIM('data cleaning'!$I32) -> South | I32: South | J32: =TRIM('data cleaning'!$K32) -> Office Supplies | K32: Office Supplies | L32: =TRIM('data cleaning'!$M32) -> Storage | M32: Storage | N32: =PROPER('data cleaning'!$O32) -> Growth Storage | O32: =TRIM('data cleaning'!$P32) -> Growth Storage | P32: Growth Storage | Q32: 351.74 | R32: 6 | S32: 0 | T32: -60.65
A33: ORD-10032 | B33: 45961 | C33: 45963 | D33: =TRIM('data cleaning'!$E33) -> Erika Ellis | E33: Erika Ellis | F33: =TRIM('data cleaning'!$G33) -> Consumer | G33: Consumer | H33: =TRIM('data cleaning'!$I33) -> West | I33: West | J33: =TRIM('data cleaning'!$K33) -> Furniture | K33: Furniture | L33: =TRIM('data cleaning'!$M33) -> Bookcases | M33: Bookcases | N33: =PROPER('data cleaning'!$O33) -> One Bookcases | O33: =TRIM('data cleaning'!$P33) -> One Bookcases | P33: One Bookcases | Q33: 4264.15 | R33: 2 | S33: 0.2 | T33: -693.44
A34: ORD-10033 | B34: 46008 | C34: 46012 | D34: =TRIM('data cleaning'!$E34) -> Pamela Norman | E34: Pamela Norman | F34: =TRIM('data cleaning'!$G34) -> Home Office | G34: Home Office | H34: =TRIM('data cleaning'!$I34) -> East | I34: East | J34: =TRIM('data cleaning'!$K34) -> Furniture | K34: Furniture | L34: =TRIM('data cleaning'!$M34) -> Bookcases | M34: Bookcases | N34: =PROPER('data cleaning'!$O34) -> Wait Bookcases | O34: =TRIM('data cleaning'!$P34) -> Wait Bookcases | P34: Wait Bookcases | Q34: 2915.65 | R34: 1 | S34: 0.2 | T34: -451.66
... A37: ORD-10036 | B37: 45724 | C37: 45726 | D37: =TRIM('data cleaning'!$E37) -> Katelyn Williams | E37: Katelyn Williams | F37: =TRIM('data cleaning'!$G37) -> Home Office | G37: Home Office | H37: =TRIM('data cleaning'!$I37) -> East | I37: East | J37: =TRIM('data cleaning'!$K37) -> Furniture | K37: Furniture | L37: =TRIM('data cleaning'!$M37) -> Tables | M37: Tables | N37: =PROPER('data cleaning'!$O37) -> Son Tables | O37: =TRIM('data cleaning'!$P37) -> Son Tables | P37: Son Tables | Q37: 4402.39 | R37: 6 | S37: 0.1 | T37: -498.52
A38: ORD-10037 | B38: 07-11-2023 | C38: 45246 | D38: =TRIM('data cleaning'!$E38) -> Shannon Wagner | E38: Shannon Wagner | F38: =TRIM('data cleaning'!$G38) -> Consumer | G38: Consumer | H38: =TRIM('data cleaning'!$I38) -> South | I38: South | J38: =TRIM('data cleaning'!$K38) -> Office Supplies | K38: Office Supplies | L38: =TRIM('data cleaning'!$M38) -> Storage | M38: Storage | N38: =PROPER('data cleaning'!$O38) -> With Storage | O38: =TRIM('data cleaning'!$P38) -> With Storage | P38: With Storage | Q38: 88.72 | R38: 9 | S38: 0.1 | T38: 27.72
A39: ORD-10038 | B39: 45815 | C39: 45817 | D39: =TRIM('data cleaning'!$E39) -> Kelli Johnson | E39: Kelli Johnson | F39: =TRIM('data cleaning'!$G39) -> Consumer | G39: Consumer | H39: =TRIM('data cleaning'!$I39) -> East | I39: East | J39: =TRIM('data cleaning'!$K39) -> Technology | K39: Technology | L39: =TRIM('data cleaning'!$M39) -> Phones | M39: Phones | N39: =PROPER('data cleaning'!$O39) -> This Phones | O39: =TRIM('data cleaning'!$P39) -> This Phones | P39: This Phones | Q39: 3724.96 | R39: 3 | S39: 0.1 | T39: -167.75
A40: ORD-10039 | B40: 45087 | C40: 45092 | D40: =TRIM('data cleaning'!$E40) -> Rebecca Blake | E40: Rebecca Blake | F40: =TRIM('data cleaning'!$G40) -> Corporate | G40: Corporate | H40: =TRIM('data cleaning'!$I40) -> East | I40: East | J40: =TRIM('data cleaning'!$K40) -> Furniture | K40: Furniture | L40: =TRIM('data cleaning'!$M40) -> Bookcases | M40: Bookcases | N40: =PROPER('data cleaning'!$O40) -> Throughout Bookcases | O40: =TRIM('data cleaning'!$P40) -> Throughout Bookcases | P40: Throughout Bookcases | Q40: 2551.77 | R40: 5 | S40: 0 | T40: -380.82
A41: ORD-10040 | B41: 46089 | C41: 46095 | D41: =TRIM('data cleaning'!$E41) -> Brian Gallagher | E41: Brian Gallagher | F41: =TRIM('data cleaning'!$G41) -> Home Office | G41: Home Office | H41: =TRIM('data cleaning'!$I41) -> West | I41: West | J41: =TRIM('data cleaning'!$K41) -> Furniture | K41: Furniture | L41: =TRIM('data cleaning'!$M41) -> Chairs | M41: Chairs | N41: =PROPER('data cleaning'!$O41) -> According Chairs | O41: =TRIM('data cleaning'!$P41) -> According Chairs | P41: According Chairs | Q41: 3867.04 | R41: 5 | S41: 0.05 | T41: 803.1
A42: ORD-10041 | B42: 45846 | C42: 45848 | D42: =TRIM('data cleaning'!$E42) -> Melissa Burgess | E42: Melissa Burgess | F42: =TRIM('data cleaning'!$G42) -> Corporate | G42: Corporate | H42: =TRIM('data cleaning'!$I42) -> South | I42: South | J42: =TRIM('data cleaning'!$K42) -> Office Supplies | K42: Office Supplies | L42: =TRIM('data cleaning'!$M42) -> Binders | M42: Binders | N42: =PROPER('data cleaning'!$O42) -> Three Binders | O42: =TRIM('data cleaning'!$P42) -> Three Binders | P42: Three Binders | Q42: 422.46 | R42: 3 | S42: 0.2 | T42: -76.12
A43: ORD-10042 | B43: 46158 | C43: 46159 | D43: =TRIM('data cleaning'!$E43) -> Jenna Hill | E43: Jenna Hill | F43: =TRIM('data cleaning'!$G43) -> Consumer | G43: Consumer | H43: =TRIM('data cleaning'!$I43) -> North | I43: North | J43: =TRIM('data cleaning'!$K43) -> Technology | K43: Technology | L43: =TRIM('data cleaning'!$M43) -> Phones | M43: Phones | N43: =PROPER('data cleaning'!$O43) -> Employee Phones | O43: =TRIM('data cleaning'!$P43) -> Employee Phones | P43: Employee Phones | Q43: 1575.88 | R43: 1 | S43: 0.1 | T43: -133.1
A44: ORD-10043 | B44: 46057 | C44: 46064 | D44: =TRIM('data cleaning'!$E44) -> Steven Moody | E44: Steven Moody | F44: =TRIM('data cleaning'!$G44) -> Consumer | G44: Consumer | H44: =TRIM('data cleaning'!$I44) -> West | I44: West | J44: =TRIM('data cleaning'!$K44) -> Technology | K44: Technology | L44: =TRIM('data cleaning'!$M44) -> Laptops | M44: Laptops | N44: =PROPER('data cleaning'!$O44) -> Writer Laptops | O44: =TRIM('data cleaning'!$P44) -> Writer Laptops | P44: Writer Laptops | Q44: 4870.49 | R44: 3 | S44: 0.05 | T44: 1341.98
A45: ORD-10044 | B45: 45839 | C45: 45845 | D45: =TRIM('data cleaning'!$E45) -> Donald Prince | E45: Donald Prince | F45: =TRIM('data cleaning'!$G45) -> Consumer | G45: Consumer | H45: =TRIM('data cleaning'!$I45) -> East | I45: East | J45: =TRIM('data cleaning'!$K45) -> Furniture | K45: Furniture | L45: =TRIM('data cleaning'!$M45) -> Chairs | M45: Chairs | N45: =PROPER('data cleaning'!$O45) -> Development Chairs | O45: =TRIM('data cleaning'!$P45) -> Development Chairs | P45: Development Chairs | Q45: 3922.81 | R45: 7 | T45: 1079.7
A46: ORD-10045 | B46: 45549 | C46: 45551 | D46: =TRIM('data cleaning'!$E46) -> Michael Robinson | E46: Michael Robinson | F46: =TRIM('data cleaning'!$G46) -> Corporate | G46: Corporate | H46: =TRIM('data cleaning'!$I46) -> East | I46: East | J46: =TRIM('data cleaning'!$K46) -> Furniture | K46: Furniture | L46: =TRIM('data cleaning'!$M46) -> Bookcases | M46: Bookcases | N46: =PROPER('data cleaning'!$O46) -> These Bookcases | O46: =TRIM('data cleaning'!$P46) -> These Bookcases | P46: These Bookcases | Q46: 1943.58 | R46: 1 | S46: 0.15 | T46: -150.94
A47: ORD-10046 | B47: 45230 | C47: 45234 | D47: =TRIM('data cleaning'!$E47) -> Christina Cooper | E47: Christina Cooper | F47: =TRIM('data cleaning'!$G47) -> Consumer | G47: Consumer | H47: =TRIM('data cleaning'!$I47) -> East | I47: East | J47: =TRIM('data cleaning'!$K47) -> Technology | K47: Technology | L47: =TRIM('data cleaning'!$M47) -> Phones | M47: Phones | N47: =PROPER('data cleaning'!$O47) -> Live Phones | O47: =TRIM('data cleaning'!$P47) -> Live Phones | P47: Live Phones | Q47: 167.14 | R47: 4 | S47: 0.15 | T47: -3.25
A48: ORD-10047 | B48: 45757 | C48: 45766 | D48: =TRIM('data cleaning'!$E48) -> David Anderson | E48: David Anderson | F48: =TRIM('data cleaning'!$G48) -> Consumer | G48: Consumer | H48: =TRIM('data cleaning'!$I48) -> East | I48: East | J48: =TRIM('data cleaning'!$K48) -> Technology | K48: Technology | L48: =TRIM('data cleaning'!$M48) -> Laptops | M48: Laptops | N48: =PROPER('data cleaning'!$O48) -> Interesting Laptops | O48: =TRIM('data cleaning'!$P48) -> Interesting Laptops | P48: Interesting Laptops | Q48: 2028.41 | R48: 9 | S48: 0.1 | T48: 642.15
A49: ORD-10048 | B49: 45409 | C49: 45414 | D49: =TRIM('data cleaning'!$E49) -> Ann Conner | E49: Ann Conner | F49: =TRIM('data cleaning'!$G49) -> Corporate | G49: Corporate | H49: =TRIM('data cleaning'!$I49) -> West | I49: West | J49: =TRIM('data cleaning'!$K49) -> Furniture | K49: Furniture | L49: =TRIM('data cleaning'!$M49) -> Bookcases | M49: Bookcases | N49: =PROPER('data cleaning'!$O49) -> Effort Bookcases | O49: =TRIM('data cleaning'!$P49) -> Effort Bookcases | P49: Effort Bookcases | Q49: 239.37 | R49: 10 | S49: 0.15 | T49: -2.36
A50: ORD-10049 | B50: 46007 | C50: 46009 | D50: =TRIM('data cleaning'!$E50) -> David Morgan | E50: David Morgan | F50: =TRIM('data cleaning'!$G50) -> Home Office | G50: Home Office | H50: =TRIM('data cleaning'!$I50) -> West | I50: West | J50: =TRIM('data cleaning'!$K50) -> Office Supplies | K50: Office Supplies | L50: =TRIM('data cleaning'!$M50) -> Storage | M50: Storage | N50: =PROPER('data cleaning'!$O50) -> Man Storage | O50: =TRIM('data cleaning'!$P50) -> Man Storage | P50: Man Storage | Q50: 1956.72 | R50: 10 | S50: 0.05 | T50: -117.21
A51: ORD-10050 | B51: 45715 | C51: 45724 | D51: =TRIM('data cleaning'!$E51) -> Andrea Carrillo | E51: Andrea Carrillo | F51: =TRIM('data cleaning'!$G51) -> Home Office | G51: Home Office | H51: =TRIM('data cleaning'!$I51) -> East | I51: East | J51: =TRIM('data cleaning'!$K51) -> Furniture | K51: Furniture | L51: =TRIM('data cleaning'!$M51) -> Bookcases | M51: Bookcases | N51: =PROPER('data cleaning'!$O51) -> Chair Bookcases | O51: =TRIM('data cleaning'!$P51) -> Chair Bookcases | P51: Chair Bookcases | Q51: 3449.94 | R51: 4 | S51: 0.1 | T51: 128.38
A52: ORD-10051 | B52: 45385 | C52: 45387 | D52: =TRIM('data cleaning'!$E52) -> Laura James | E52: Laura James | F52: =TRIM('data cleaning'!$G52) -> Corporate | G52: Corporate | H52: =TRIM('data cleaning'!$I52) -> East | I52: East | J52: =TRIM('data cleaning'!$K52) -> Office Supplies | K52: Office Supplies | L52: =TRIM('data cleaning'!$M52) -> Paper | M52: Paper | N52: =PROPER('data cleaning'!$O52) -> News Paper | O52: =TRIM('data cleaning'!$P52) -> News Paper | P52: News Paper | Q52: 3612.78 | R52: 5 | S52: 0.2 | T52: -108
A53: ORD-10052 | B53: 45830 | C53: 45835 | D53: =TRIM('data cleaning'!$E53) -> Charles Torres | E53: Charles Torres | F53: =TRIM('data cleaning'!$G53) -> Corporate | G53: Corporate | H53: =TRIM('data cleaning'!$I53) -> South | I53: South | J53: =TRIM('data cleaning'!$K53) -> Technology | K53: Technology | L53: =TRIM('data cleaning'!$M53) -> Laptops | M53: Laptops | N53: =PROPER('data cleaning'!$O53) -> Open Laptops | O53: =TRIM('data cleaning'!$P53) -> Open Laptops | P53: Open Laptops | Q53: 2794.34 | R53: 4 | S53: 0.15 | T53: 463.05
A54: ORD-10053 | B54: 24-01-2024 | C54: 45320 | D54: =TRIM('data cleaning'!$E54) -> Alexander Taylor | E54: Alexander Taylor | F54: =TRIM('data cleaning'!$G54) -> Corporate | G54: Corporate | H54: =TRIM('data cleaning'!$I54) -> East | I54: East | J54: =TRIM('data cleaning'!$K54) -> Office Supplies | K54: Office Supplies | L54: =TRIM('data cleaning'!$M54) -> Storage | M54: Storage | N54: =PROPER('data cleaning'!$O54) -> History Storage | O54: =TRIM('data cleaning'!$P54) -> History Storage | P54: History Storage | Q54: 2060.07 | R54: 1 | S54: 0.1 | T54: -86.93
A55: ORD-10054 | B55: 45939 | C55: 45947 | D55: =TRIM('data cleaning'!$E55) -> Walter Lindsey | E55: Walter Lindsey | F55: =TRIM('data cleaning'!$G55) -> Home Office | G55: Home Office | H55: =TRIM('data cleaning'!$I55) -> South | I55: South | J55: =TRIM('data cleaning'!$K55) -> Technology | K55: Technology | L55: =TRIM('data cleaning'!$M55) -> Accessories | M55: Accessories | N55: =PROPER('data cleaning'!$O55) -> Stay Accessories | O55: =TRIM('data cleaning'!$P55) -> Stay Accessories | P55: Stay Accessories | Q55: 3394.35 | R55: 9 | S55: 0.15 | T55: 802.95
A56: ORD-10055 | B56: 45720 | C56: 45725 | D56: =TRIM('data cleaning'!$E56) -> Jennifer Downs | E56: Jennifer Downs | F56: =TRIM('data cleaning'!$G56) -> Consumer | G56: Consumer | H56: =TRIM('data cleaning'!$I56) -> East | I56: East | J56: =TRIM('data cleaning'!$K56) -> Office Supplies | K56: Office Supplies | L56: =TRIM('data cleaning'!$M56) -> Binders | M56: Binders | N56: =PROPER('data cleaning'!$O56) -> Support Binders | O56: =TRIM('data cleaning'!$P56) -> Support Binders | P56: Support Binders | Q56: 2601.49 | R56: 10 | S56: 0.1 | T56: -386.68
A57: ORD-10056 | B57: 45424 | C57: 45427 | D57: =TRIM('data cleaning'!$E57) -> Tara Ferguson | E57: Tara Ferguson | F57: =TRIM('data cleaning'!$G57) -> Consumer | G57: Consumer | H57: =TRIM('data cleaning'!$I57) -> West | I57: West | J57: =TRIM('data cleaning'!$K57) -> Furniture | K57: Furniture | L57: =TRIM('data cleaning'!$M57) -> Chairs | M57: Chairs | N57: =PROPER('data cleaning'!$O57) -> Just Chairs | O57: =TRIM('data cleaning'!$P57) -> Just Chairs | P57: Just Chairs | Q57: 170.91 | R57: 4 | S57: 0.15 | T57: 23.28
A58: ORD-10057 | B58: 45773 | C58: 45783 | D58: =TRIM('data cleaning'!$E58) -> Brittany Woodward | E58: Brittany Woodward | F58: =TRIM('data cleaning'!$G58) -> Consumer | G58: Consumer | H58: =TRIM('data cleaning'!$I58) -> North | I58: North | J58: =TRIM('data cleaning'!$K58) -> Technology | K58: Technology | L58: =TRIM('data cleaning'!$M58) -> Laptops | M58: Laptops | N58: =PROPER('data cleaning'!$O58) -> Laugh Laptops | O58: =TRIM('data cleaning'!$P58) -> Laugh Laptops | P58: Laugh Laptops | Q58: 1012.45 | R58: 7 | S58: 0.15 | T58: 20.06
A59: ORD-10058 | B59: 45366 | C59: 45370 | D59: =TRIM('data cleaning'!$E59) -> Johnathan Logan | E59: Johnathan Logan | F59: =TRIM('data cleaning'!$G59) -> Consumer | G59: Consumer | H59: =TRIM('data cleaning'!$I59) -> North | I59: North | J59: =TRIM('data cleaning'!$K59) -> Furniture | K59: Furniture | L59: =TRIM('data cleaning'!$M59) -> Tables | M59: Tables | N59: =PROPER('data cleaning'!$O59) -> Baby Tables | O59: =TRIM('data cleaning'!$P59) -> Baby Tables | P59: Baby Tables | Q59: 920.64 | R59: 9 | S59: 0.15 | T59: -158.7
A60: ORD-10059 | B60: 45364 | C60: 45372 | D60: =TRIM('data cleaning'!$E60) -> Maria Walker | E60: Maria Walker | F60: =TRIM('data cleaning'!$G60) -> Corporate | G60: Corporate | H60: =TRIM('data cleaning'!$I60) -> West | I60: West | J60: =TRIM('data cleaning'!$K60) -> Technology | K60: Technology | L60: =TRIM('data cleaning'!$M60) -> Phones | M60: Phones | N60: =PROPER('data cleaning'!$O60) -> Memory Phones | O60: =TRIM('data cleaning'!$P60) -> Memory Phones | P60: Memory Phones | Q60: 3354.51 | R60: 9 | S60: 0.2 | T60: -85.49
A61: ORD-10060 | B61: 45861 | C61: 45864 | D61: =TRIM('data cleaning'!$E61) -> Robert Willis | E61: Robert Willis | F61: =TRIM('data cleaning'!$G61) -> Consumer | G61: Consumer | H61: =TRIM('data cleaning'!$I61) -> East | I61: East | J61: =TRIM('data cleaning'!$K61) -> Office Supplies | K61: Office Supplies | L61: =TRIM('data cleaning'!$M61) -> Paper | M61: Paper | N61: =PROPER('data cleaning'!$O61) -> Different Paper | O61: =TRIM('data cleaning'!$P61) -> Different Paper | P61: Different Paper | Q61: 3731.09 | R61: 8 | S61: 0.15 | T61: -214.33
A62: ORD-10061 | B62: 45691 | C62: 45695 | D62: =TRIM('data cleaning'!$E62) -> Wanda Byrd | E62: Wanda Byrd | F62: =TRIM('data cleaning'!$G62) -> Corporate | G62: Corporate | H62: =TRIM('data cleaning'!$I62) -> East | I62: East | J62: =TRIM('data cleaning'!$K62) -> Office Supplies | K62: Office Supplies | L62: =TRIM('data cleaning'!$M62) -> Paper | M62: Paper | N62: =PROPER('data cleaning'!$O62) -> Fact Paper | O62: =TRIM('data cleaning'!$P62) -> Fact Paper | P62: Fact Paper | Q62: 1409.26 | R62: 2 | T62: -60.39
A63: ORD-10062 | B63: 45190 | C63: 45192 | D63: =TRIM('data cleaning'!$E63) -> John Potts | E63: John Potts | F63: =TRIM('data cleaning'!$G63) -> Home Office | G63: Home Office | H63: =TRIM('data cleaning'!$I63) -> South | I63: South | J63: =TRIM('data cleaning'!$K63) -> Technology | K63: Technology | L63: =TRIM('data cleaning'!$M63) -> Laptops | M63: Laptops | N63: =PROPER('data cleaning'!$O63) -> Shake Laptops | O63: =TRIM('data cleaning'!$P63) -> Shake Laptops | P63: Shake Laptops | Q63: 734.95 | R63: 4 | S63: 0.15 | T63: 133.52
A64: ORD-10063 | B64: 45390 | C64: 45397 | D64: =TRIM('data cleaning'!$E64) -> Monica Kelley | E64: Monica Kelley | F64: =TRIM('data cleaning'!$G64) -> Corporate | G64: Corporate | H64: =TRIM('data cleaning'!$I64) -> West | I64: West | J64: =TRIM('data cleaning'!$K64) -> Furniture | K64: Furniture | L64: =TRIM('data cleaning'!$M64) -> Tables | M64: Tables | N64: =PROPER('data cleaning'!$O64) -> Power Tables | O64: =TRIM('data cleaning'!$P64) -> Power Tables | P64: Power Tables | Q64: 1687.86 | R64: 8 | S64: 0.15 | T64: -279.77
A65: ORD-10064 | B65: 45373 | C65: 45374 | D65: =TRIM('data cleaning'!$E65) -> Justin Farrell | E65: Justin Farrell | F65: =TRIM('data cleaning'!$G65) -> Corporate | G65: Corporate | H65: =TRIM('data cleaning'!$I65) -> East | I65: East | J65: =TRIM('data cleaning'!$K65) -> Office Supplies | K65: Office Supplies | L65: =TRIM('data cleaning'!$M65) -> Storage | M65: Storage | N65: =PROPER('data cleaning'!$O65) -> These Storage | O65: =TRIM('data cleaning'!$P65) -> These Storage | P65: These Storage | Q65: 4290.82 | R65: 10 | S65: 0.15 | T65: 267.48
A66: ORD-10065 | B66: 46122 | C66: 46131 | D66: =TRIM('data cleaning'!$E66) -> Joseph Sanchez | E66: Joseph Sanchez | F66: =TRIM('data cleaning'!$G66) -> Corporate | G66: Corporate | H66: =TRIM('data cleaning'!$I66) -> South | I66: South | J66: =TRIM('data cleaning'!$K66) -> Technology | K66: Technology | L66: =TRIM('data cleaning'!$M66) -> Accessories | M66: Accessories | N66: =PROPER('data cleaning'!$O66) -> Still Accessories | O66: =TRIM('data cleaning'!$P66) -> Still Accessories | P66: Still Accessories | Q66: 3750.2 | R66: 9 | S66: 0.2 | T66: 1101.79
A67: ORD-10066 | B67: 45482 | C67: 45490 | D67: =TRIM('data cleaning'!$E67) -> Kenneth Dunn | E67: Kenneth Dunn | F67: =TRIM('data cleaning'!$G67) -> Corporate | G67: Corporate | H67: =TRIM('data cleaning'!$I67) -> South | I67: South | J67: =TRIM('data cleaning'!$K67) -> Technology | K67: Technology | L67: =TRIM('data cleaning'!$M67) -> Accessories | M67: Accessories | N67: =PROPER('data cleaning'!$O67) -> Interest Accessories | O67: =TRIM('data cleaning'!$P67) -> Interest Accessories | P67: Interest Accessories | Q67: 193.67 | R67: 6 | T67: 33.61
A68: ORD-10067 | B68: 45134 | C68: 45144 | D68: =TRIM('data cleaning'!$E68) -> Christina Henry | E68: Christina Henry | F68: =TRIM('data cleaning'!$G68) -> Consumer | G68: Consumer | H68: =TRIM('data cleaning'!$I68) -> North | I68: North | J68: =TRIM('data cleaning'!$K68) -> Technology | K68: Technology | L68: =TRIM('data cleaning'!$M68) -> Phones | M68: Phones | N68: =PROPER('data cleaning'!$O68) -> Moment Phones | O68: =TRIM('data cleaning'!$P68) -> Moment Phones | P68: Moment Phones | Q68: 2693.91 | R68: 7 | S68: 0.2 | T68: 297.45
A69: ORD-10068 | B69: 46123 | C69: 46126 | D69: =TRIM('data cleaning'!$E69) -> Jessica Smith | E69: Jessica Smith | F69: =TRIM('data cleaning'!$G69) -> Corporate | G69: Corporate | H69: =TRIM('data cleaning'!$I69) -> South | I69: South | J69: =TRIM('data cleaning'!$K69) -> Office Supplies | K69: Office Supplies | L69: =TRIM('data cleaning'!$M69) -> Paper | M69: Paper | N69: =PROPER('data cleaning'!$O69) -> Write Paper | O69: =TRIM('data cleaning'!$P69) -> Write Paper | P69: Write Paper | Q69: 4340.91 | R69: 3 | S69: 0 | T69: -247.06
A70: ORD-10069 | B70: 45148 | C70: 45154 | D70: =TRIM('data cleaning'!$E70) -> Daniel Williamson | E70: Daniel Williamson | F70: =TRIM('data cleaning'!$G70) -> Corporate | G70: Corporate | H70: =TRIM('data cleaning'!$I70) -> East | I70: East | J70: =TRIM('data cleaning'!$K70) -> Technology | K70: Technology | L70: =TRIM('data cleaning'!$M70) -> Accessories | M70: Accessories | N70: =PROPER('data cleaning'!$O70) -> By Accessories | O70: =TRIM('data cleaning'!$P70) -> By Accessories | P70: By Accessories | Q70: 3818.09 | R70: 7 | S70: 0.1 | T70: 815.56
A71: ORD-10070 | B71: 45993 | C71: 45994 | D71: =TRIM('data cleaning'!$E71) -> Sean Miranda | E71: Sean Miranda | F71: =TRIM('data cleaning'!$G71) -> Consumer | G71: Consumer | H71: =TRIM('data cleaning'!$I71) -> North | I71: North | J71: =TRIM('data cleaning'!$K71) -> Furniture | K71: Furniture | L71: =TRIM('data cleaning'!$M71) -> Tables | M71: Tables | N71: =PROPER('data cleaning'!$O71) -> Number Tables | O71: =TRIM('data cleaning'!$P71) -> Number Tables | P71: Number Tables | Q71: 3757.67 | R71: 1 | S71: 0.1 | T71: -288.13
A72: ORD-10071 | B72: 45264 | C72: 45268 | D72: =TRIM('data cleaning'!$E72) -> Kelly Yoder | E72: Kelly Yoder | F72: =TRIM('data cleaning'!$G72) -> Corporate | G72: Corporate | H72: =TRIM('data cleaning'!$I72) -> North | I72: North | J72: =TRIM('data cleaning'!$K72) -> Furniture | K72: Furniture | L72: =TRIM('data cleaning'!$M72) -> Chairs | M72: Chairs | N72: =PROPER('data cleaning'!$O72) -> Next Chairs | O72: =TRIM('data cleaning'!$P72) -> Next Chairs | P72: Next Chairs | Q72: 4204.18 | R72: 10 | S72: 0.05 | T72: -289.25
A73: ORD-10072 | B73: 45102 | C73: 45110 | D73: =TRIM('data cleaning'!$E73) -> Cristian Graham | E73: Cristian Graham | F73: =TRIM('data cleaning'!$G73) -> Home Office | G73: Home Office | H73: =TRIM('data cleaning'!$I73) -> North | I73: North | J73: =TRIM('data cleaning'!$K73) -> Office Supplies | K73: Office Supplies | L73: =TRIM('data cleaning'!$M73) -> Binders | M73: Binders | N73: =PROPER('data cleaning'!$O73) -> Back Binders | O73: =TRIM('data cleaning'!$P73) -> Back Binders | P73: Back Binders | Q73: 3512.35 | R73: 6 | S73: 0.05 | T73: 467.99
A74: ORD-10073 | B74: 45081 | C74: 45083 | D74: =TRIM('data cleaning'!$E74) -> Patricia Rojas | E74: Patricia Rojas | F74: =TRIM('data cleaning'!$G74) -> Corporate | G74: Corporate | H74: =TRIM('data cleaning'!$I74) -> West | I74: West | J74: =TRIM('data cleaning'!$K74) -> Furniture | K74: Furniture | L74: =TRIM('data cleaning'!$M74) -> Tables | M74: Tables | N74: =PROPER('data cleaning'!$O74) -> Despite Tables | O74: =TRIM('data cleaning'!$P74) -> Despite Tables | P74: Despite Tables | Q74: 2914.49 | R74: 5 | S74: 0.2 | T74: 502.87
A75: ORD-10074 | B75: 45992 | C75: 45994 | D75: =TRIM('data cleaning'!$E75) -> Elizabeth Martin | E75: Elizabeth Martin | F75: =TRIM('data cleaning'!$G75) -> Corporate | G75: Corporate | H75: =TRIM('data cleaning'!$I75) -> North | I75: North | J75: =TRIM('data cleaning'!$K75) -> Office Supplies | K75: Office Supplies | L75: =TRIM('data cleaning'!$M75) -> Binders | M75: Binders | N75: =PROPER('data cleaning'!$O75) -> Generation Binders | O75: =TRIM('data cleaning'!$P75) -> Generation Binders | P75: Generation Binders | Q75: 2980.88 | R75: 4 | S75: 0 | T75: 546.86
A76: ORD-10075 | B76: 45071 | C76: 45077 | D76: =TRIM('data cleaning'!$E76) -> Mr. Nicholas Fischer III | E76: Mr. Nicholas Fischer III | F76: =TRIM('data cleaning'!$G76) -> Corporate | G76: Corporate | H76: =TRIM('data cleaning'!$I76) -> North | I76: North | J76: =TRIM('data cleaning'!$K76) -> Office Supplies | K76: Office Supplies | L76: =TRIM('data cleaning'!$M76) -> Binders | M76: Binders | N76: =PROPER('data cleaning'!$O76) -> Whose Binders | O76: =TRIM('data cleaning'!$P76) -> Whose Binders | P76: Whose Binders | Q76: 2687.09 | R76: 6 | S76: 0 | T76: 210.34
A77: ORD-10076 | B77: 45370 | C77: 45372 | D77: =TRIM('data cleaning'!$E77) -> Michael Whitney | E77: Michael Whitney | F77: =TRIM('data cleaning'!$G77) -> Corporate | G77: Corporate | H77: =TRIM('data cleaning'!$I77) -> South | I77: South | J77: =TRIM('data cleaning'!$K77) -> Technology | K77: Technology | L77: =TRIM('data cleaning'!$M77) -> Accessories | M77: Accessories | N77: =PROPER('data cleaning'!$O77) -> Give Accessories | O77: =TRIM('data cleaning'!$P77) -> Give Accessories | P77: Give Accessories | Q77: 2195.94 | R77: 6 | T77: 637.63
A78: ORD-10077 | B78: 17-09-2023 | C78: 45195 | D78: =TRIM('data cleaning'!$E78) -> William Gonzalez | E78: William Gonzalez | F78: =TRIM('data cleaning'!$G78) -> Home Office | G78: Home Office | H78: =TRIM('data cleaning'!$I78) -> West | I78: West | J78: =TRIM('data cleaning'!$K78) -> Technology | K78: Technology | L78: =TRIM('data cleaning'!$M78) -> Phones | M78: Phones | N78: =PROPER('data cleaning'!$O78) -> Type Phones | O78: =TRIM('data cleaning'!$P78) -> Type Phones | P78: Type Phones | Q78: 4829.09 | R78: 5 | S78: 0.2 | T78: 1180.76
A79: ORD-10078 | B79: 45614 | C79: 45624 | D79: =TRIM('data cleaning'!$E79) -> Gabriel Daniels | E79: Gabriel Daniels | F79: =TRIM('data cleaning'!$G79) -> Corporate | G79: Corporate | H79: =TRIM('data cleaning'!$I79) -> South | I79: South | J79: =TRIM('data cleaning'!$K79) -> Technology | K79: Technology | L79: =TRIM('data cleaning'!$M79) -> Accessories | M79: Accessories | N79: =PROPER('data cleaning'!$O79) -> Theory Accessories | O79: =TRIM('data cleaning'!$P79) -> Theory Accessories | P79: Theory Accessories | Q79: 1378.56 | R79: 4 | S79: 0 | T79: -64.23
A80: ORD-10079 | B80: 45551 | C80: 45561 | D80: =TRIM('data cleaning'!$E80) -> Monica Price | E80: Monica Price | F80: =TRIM('data cleaning'!$G80) -> Corporate | G80: Corporate | H80: =TRIM('data cleaning'!$I80) -> South | I80: South | J80: =TRIM('data cleaning'!$K80) -> Technology | K80: Technology | L80: =TRIM('data cleaning'!$M80) -> Laptops | M80: Laptops | N80: =PROPER('data cleaning'!$O80) -> While Laptops | O80: =TRIM('data cleaning'!$P80) -> While Laptops | P80: While Laptops | Q80: 3357.53 | R80: 6 | S80: 0 | T80: 241.3
A81: ORD-10080 | B81: 45485 | C81: 45491 | D81: =TRIM('data cleaning'!$E81) -> Christine Wood | E81: Christine Wood | F81: =TRIM('data cleaning'!$G81) -> Home Office | G81: Home Office | H81: =TRIM('data cleaning'!$I81) -> East | I81: East | J81: =TRIM('data cleaning'!$K81) -> Technology | K81: Technology | L81: =TRIM('data cleaning'!$M81) -> Phones | M81: Phones | N81: =PROPER('data cleaning'!$O81) -> Wrong Phones | O81: =TRIM('data cleaning'!$P81) -> Wrong Phones | P81: Wrong Phones | Q81: 3999.27 | R81: 6 | S81: 0.1 | T81: 1136.5
A82: ORD-10081 | B82: 45493 | C82: 45502 | D82: =TRIM('data cleaning'!$E82) -> Christopher Becker | E82: Christopher Becker | F82: =TRIM('data cleaning'!$G82) -> Corporate | G82: Corporate | H82: =TRIM('data cleaning'!$I82) -> South | I82: South | J82: =TRIM('data cleaning'!$K82) -> Office Supplies | K82: Office Supplies | L82: =TRIM('data cleaning'!$M82) -> Binders | M82: Binders | N82: =PROPER('data cleaning'!$O82) -> It Binders | O82: =TRIM('data cleaning'!$P82) -> It Binders | P82: It Binders | Q82: 4742.91 | R82: 2 | S82: 0.05 | T82: 929.81
A83: ORD-10082 | B83: 45411 | C83: 45419 | D83: =TRIM('data cleaning'!$E83) -> Brandon Barker | E83: Brandon Barker | F83: =TRIM('data cleaning'!$G83) -> Corporate | G83: Corporate | H83: =TRIM('data cleaning'!$I83) -> South | I83: South | J83: =TRIM('data cleaning'!$K83) -> Office Supplies | K83: Office Supplies | L83: =TRIM('data cleaning'!$M83) -> Paper | M83: Paper | N83: =PROPER('data cleaning'!$O83) -> Everybody Paper | O83: =TRIM('data cleaning'!$P83) -> Everybody Paper | P83: Everybody Paper | Q83: 2268.46 | R83: 1 | S83: 0 | T83: -86.59
A84: ORD-10083 | B84: 45827 | C84: 45837 | D84: =TRIM('data cleaning'!$E84) -> Teresa Velazquez | E84: Teresa Velazquez | F84: =TRIM('data cleaning'!$G84) -> Home Office | G84: Home Office | H84: =TRIM('data cleaning'!$I84) -> East | I84: East | J84: =TRIM('data cleaning'!$K84) -> Technology | K84: Technology | L84: =TRIM('data cleaning'!$M84) -> Laptops | M84: Laptops | N84: =PROPER('data cleaning'!$O84) -> Power Laptops | O84: =TRIM('data cleaning'!$P84) -> Power Laptops | P84: Power Laptops | Q84: 1876.65 | R84: 9 | S84: 0.2 | T84: -20.52
A85: ORD-10084 | B85: 45676 | C85: 45684 | D85: =TRIM('data cleaning'!$E85) -> Kristen Payne | E85: Kristen Payne | F85: =TRIM('data cleaning'!$G85) -> Consumer | G85: Consumer | H85: =TRIM('data cleaning'!$I85) -> East | I85: East | J85: =TRIM('data cleaning'!$K85) -> Technology | K85: Technology | L85: =TRIM('data cleaning'!$M85) -> Laptops | M85: Laptops | N85: =PROPER('data cleaning'!$O85) -> Small Laptops | O85: =TRIM('data cleaning'!$P85) -> Small Laptops | P85: Small Laptops | Q85: 1391.04 | R85: 5 | S85: 0.05 | T85: -185.9
A86: ORD-10085 | B86: 45138 | C86: 45147 | D86: =TRIM('data cleaning'!$E86) -> Brittany Bradley | E86: Brittany Bradley | F86: =TRIM('data cleaning'!$G86) -> Corporate | G86: Corporate | H86: =TRIM('data cleaning'!$I86) -> East | I86: East | J86: =TRIM('data cleaning'!$K86) -> Furniture | K86: Furniture | L86: =TRIM('data cleaning'!$M86) -> Bookcases | M86: Bookcases | N86: =PROPER('data cleaning'!$O86) -> Adult Bookcases | O86: =TRIM('data cleaning'!$P86) -> Adult Bookcases | P86: Adult Bookcases | Q86: 4756.84 | R86: 3 | S86: 0.05 | T86: -385.25
A87: ORD-10086 | B87: 45760 | C87: 45769 | D87: =TRIM('data cleaning'!$E87) -> Christy Harris | E87: Christy Harris | F87: =TRIM('data cleaning'!$G87) -> Corporate | G87: Corporate | H87: =TRIM('data cleaning'!$I87) -> South | I87: South | J87: =TRIM('data cleaning'!$K87) -> Office Supplies | K87: Office Supplies | L87: =TRIM('data cleaning'!$M87) -> Storage | M87: Storage | N87: =PROPER('data cleaning'!$O87) -> Fear Storage | O87: =TRIM('data cleaning'!$P87) -> Fear Storage | P87: Fear Storage | Q87: 3004.11 | R87: 2 | S87: 0.05 | T87: -111.35
A88: ORD-10087 | B88: 45796 | C88: 45805 | D88: =TRIM('data cleaning'!$E88) -> Jeremy Hood | E88: Jeremy Hood | F88: =TRIM('data cleaning'!$G88) -> Home Office | G88: Home Office | H88: =TRIM('data cleaning'!$I88) -> South | I88: South | J88: =TRIM('data cleaning'!$K88) -> Technology | K88: Technology | L88: =TRIM('data cleaning'!$M88) -> Phones | M88: Phones | N88: =PROPER('data cleaning'!$O88) -> Drug Phones | O88: =TRIM('data cleaning'!$P88) -> Drug Phones | P88: Drug Phones | Q88: 676.59 | R88: 1 | S88: 0 | T88: 70.6
A89: ORD-10088 | B89: 46021 | C89: 46023 | D89: =TRIM('data cleaning'!$E89) -> Daniel Clark | E89: Daniel Clark | F89: =TRIM('data cleaning'!$G89) -> Corporate | G89: Corporate | H89: =TRIM('data cleaning'!$I89) -> East | I89: East | J89: =TRIM('data cleaning'!$K89) -> Office Supplies | K89: Office Supplies | L89: =TRIM('data cleaning'!$M89) -> Paper | M89: Paper | N89: =PROPER('data cleaning'!$O89) -> Since Paper | O89: =TRIM('data cleaning'!$P89) -> Since Paper | P89: Since Paper | Q89: 4369.96 | R89: 10 | S89: 0.1 | T89: 254.19
A90: ORD-10089 | B90: 45878 | C90: 45883 | D90: =TRIM('data cleaning'!$E90) -> Jill Ayers | E90: Jill Ayers | F90: =TRIM('data cleaning'!$G90) -> Corporate | G90: Corporate | H90: =TRIM('data cleaning'!$I90) -> West | I90: West | J90: =TRIM('data cleaning'!$K90) -> Furniture | K90: Furniture | L90: =TRIM('data cleaning'!$M90) -> Chairs | M90: Chairs | N90: =PROPER('data cleaning'!$O90) -> Third Chairs | O90: =TRIM('data cleaning'!$P90) -> Third Chairs | P90: Third Chairs | Q90: 4708.26 | R90: 8 | S90: 0 | T90: 1187.25
... A96: ORD-10095 | B96: 45871 | C96: 45879 | D96: =TRIM('data cleaning'!$E96) -> Amanda Watkins | E96: Amanda Watkins | F96: =TRIM('data cleaning'!$G96) -> Home Office | G96: Home Office | H96: =TRIM('data cleaning'!$I96) -> South | I96: South | J96: =TRIM('data cleaning'!$K96) -> Office Supplies | K96: Office Supplies | L96: =TRIM('data cleaning'!$M96) -> Paper | M96: Paper | N96: =PROPER('data cleaning'!$O96) -> What Paper | O96: =TRIM('data cleaning'!$P96) -> What Paper | P96: What Paper | Q96: 402.34 | R96: 4 | S96: 0.1 | T96: 93.87
A97: ORD-10096 | B97: 17-08-2024 | C97: 45530 | D97: =TRIM('data cleaning'!$E97) -> Kimberly Wood | E97: Kimberly Wood | F97: =TRIM('data cleaning'!$G97) -> Consumer | G97: Consumer | H97: =TRIM('data cleaning'!$I97) -> North | I97: North | J97: =TRIM('data cleaning'!$K97) -> Technology | K97: Technology | L97: =TRIM('data cleaning'!$M97) -> Phones | M97: Phones | N97: =PROPER('data cleaning'!$O97) -> Admit Phones | O97: =TRIM('data cleaning'!$P97) -> Admit Phones | P97: Admit Phones | Q97: 1162.81 | R97: 3 | S97: 0.1 | T97: 296.11
A98: ORD-10097 | B98: 45298 | C98: 45308 | D98: =TRIM('data cleaning'!$E98) -> Eric Collins | E98: Eric Collins | F98: =TRIM('data cleaning'!$G98) -> Corporate | G98: Corporate | H98: =TRIM('data cleaning'!$I98) -> East | I98: East | J98: =TRIM('data cleaning'!$K98) -> Furniture | K98: Furniture | L98: =TRIM('data cleaning'!$M98) -> Tables | M98: Tables | N98: =PROPER('data cleaning'!$O98) -> Year Tables | O98: =TRIM('data cleaning'!$P98) -> Year Tables | P98: Year Tables | Q98: 3757.34 | R98: 10 | S98: 0.1 | T98: 156.06
A99: ORD-10098 | B99: 45299 | C99: 45304 | D99: =TRIM('data cleaning'!$E99) | F99: =TRIM('data cleaning'!$G99) -> Consumer | G99: Consumer | H99: =TRIM('data cleaning'!$I99) -> West | I99: West | J99: =TRIM('data cleaning'!$K99) -> Office Supplies | K99: Office Supplies | L99: =TRIM('data cleaning'!$M99) -> Paper | M99: Paper | N99: =PROPER('data cleaning'!$O99) -> Chance Paper | O99: =TRIM('data cleaning'!$P99) -> Chance Paper | P99: Chance Paper | Q99: 2527.34 | R99: 8 | S99: 0.15 | T99: -393.65
A100: ORD-10099 | B100: 45936 | C100: 45946 | D100: =TRIM('data cleaning'!$E100) -> Yolanda Burke | E100: Yolanda Burke | F100: =TRIM('data cleaning'!$G100) -> Home Office | G100: Home Office | H100: =TRIM('data cleaning'!$I100) -> North | I100: North | J100: =TRIM('data cleaning'!$K100) -> Office Supplies | K100: Office Supplies | L100: =TRIM('data cleaning'!$M100) -> Paper | M100: Paper | N100: =PROPER('data cleaning'!$O100) -> Fall Paper | O100: =TRIM('data cleaning'!$P100) -> Fall Paper | P100: Fall Paper | Q100: 1289.32 | R100: 2 | S100: 0.05 | T100: 424.25
A101: ORD-10100 | B101: 46108 | C101: 46118 | D101: =TRIM('data cleaning'!$E101) -> Sara Miller | E101: Sara Miller | F101: =TRIM('data cleaning'!$G101) -> Corporate | G101: Corporate | H101: =TRIM('data cleaning'!$I101) -> East | I101: East | J101: =TRIM('data cleaning'!$K101) -> Office Supplies | K101: Office Supplies | L101: =TRIM('data cleaning'!$M101) -> Paper | M101: Paper | N101: =PROPER('data cleaning'!$O101) -> Song Paper | O101: =TRIM('data cleaning'!$P101) -> Song Paper | P101: Song Paper | Q101: 249.15 | R101: 3 | S101: 0.15 | T101: 21.28
A102: ORD-10101 | B102: 45449 | C102: 45456 | D102: =TRIM('data cleaning'!$E102) -> Jacqueline Hernandez | E102: Jacqueline Hernandez | F102: =TRIM('data cleaning'!$G102) -> Corporate | G102: Corporate | H102: =TRIM('data cleaning'!$I102) -> East | I102: East | J102: =TRIM('data cleaning'!$K102) -> Furniture | K102: Furniture | L102: =TRIM('data cleaning'!$M102) -> Bookcases | M102: Bookcases | N102: =PROPER('data cleaning'!$O102) -> End Bookcases | O102: =TRIM('data cleaning'!$P102) -> End Bookcases | P102: End Bookcases | Q102: 3192.18 | R102: 8 | S102: 0 | T102: 186.76
A103: ORD-10102 | B103: 45625 | C103: 45627 | D103: =TRIM('data cleaning'!$E103) -> Frederick Norris | E103: Frederick Norris | F103: =TRIM('data cleaning'!$G103) -> Corporate | G103: Corporate | H103: =TRIM('data cleaning'!$I103) -> West | I103: West | J103: =TRIM('data cleaning'!$K103) -> Technology | K103: Technology | L103: =TRIM('data cleaning'!$M103) -> Laptops | M103: Laptops | N103: =PROPER('data cleaning'!$O103) -> Role Laptops | O103: =TRIM('data cleaning'!$P103) -> Role Laptops | P103: Role Laptops | Q103: 4295.78 | R103: 6 | S103: 0.15 | T103: 779.77
A104: ORD-10103 | B104: 45636 | C104: 45644 | D104: =TRIM('data cleaning'!$E104) -> Richard Day | E104: Richard Day | F104: =TRIM('data cleaning'!$G104) -> Corporate | G104: Corporate | H104: =TRIM('data cleaning'!$I104) -> North | I104: North | J104: =TRIM('data cleaning'!$K104) -> Office Supplies | K104: Office Supplies | L104: =TRIM('data cleaning'!$M104) -> Binders | M104: Binders | N104: =PROPER('data cleaning'!$O104) -> Money Binders | O104: =TRIM('data cleaning'!$P104) -> Money Binders | P104: Money Binders | Q104: 485.9 | R104: 5 | S104: 0.1 | T104: -66.2
A105: ORD-10104 | B105: 46150 | C105: 46158 | D105: =TRIM('data cleaning'!$E105) -> Michelle Ryan | E105: Michelle Ryan | F105: =TRIM('data cleaning'!$G105) -> Corporate | G105: Corporate | H105: =TRIM('data cleaning'!$I105) -> West | I105: West | J105: =TRIM('data cleaning'!$K105) -> Office Supplies | K105: Office Supplies | L105: =TRIM('data cleaning'!$M105) -> Storage | M105: Storage | N105: =PROPER('data cleaning'!$O105) -> Somebody Storage | O105: =TRIM('data cleaning'!$P105) -> Somebody Storage | P105: Somebody Storage | Q105: 2095.58 | R105: 4 | S105: 0.2 | T105: -2.14
A106: ORD-10105 | B106: 45213 | C106: 45218 | D106: =TRIM('data cleaning'!$E106) -> Robert Rice | E106: Robert Rice | F106: =TRIM('data cleaning'!$G106) -> Corporate | G106: Corporate | H106: =TRIM('data cleaning'!$I106) | J106: =TRIM('data cleaning'!$K106) -> Furniture | K106: Furniture | L106: =TRIM('data cleaning'!$M106) -> Chairs | M106: Chairs | N106: =PROPER('data cleaning'!$O106) -> Manager Chairs | O106: =TRIM('data cleaning'!$P106) -> Manager Chairs | P106: Manager Chairs | Q106: 2768.64 | R106: 5 | S106: 0.15 | T106: 787.58
A107: ORD-10106 | B107: 45551 | C107: 45561 | D107: =TRIM('data cleaning'!$E107) -> Samantha Hernandez PhD | E107: Samantha Hernandez PhD | F107: =TRIM('data cleaning'!$G107) -> Home Office | G107: Home Office | H107: =TRIM('data cleaning'!$I107) -> West | I107: West | J107: =TRIM('data cleaning'!$K107) -> Furniture | K107: Furniture | L107: =TRIM('data cleaning'!$M107) -> Bookcases | M107: Bookcases | N107: =PROPER('data cleaning'!$O107) -> Something Bookcases | O107: =TRIM('data cleaning'!$P107) -> Something Bookcases | P107: Something Bookcases | Q107: 4006.6 | R107: 3 | S107: 0.1 | T107: 412.53
...

Sheet cleaned data
A1: Order ID | B1: Order Date | C1: Ship Date | D1: Customer Name | E1: Segment | F1: Region | G1: Category | H1: Sub-Category | I1: Product Name | J1: Sales | K1: Quantity | L1: Discount | M1: Profit | N1: Profit Status
A2: ORD-10327 | B2: 45073 | C2: 45075 | D2: Michael Li | E2: Consumer | F2: West | G2: Furniture | H2: Tables | I2: While Tables | J2: 2907.87 | K2: 9 | L2: 0.05 | M2: 3.45 | N2: =IF(Table3[[#This Row],[Profit]]<0,"Loss","Profit") -> Profit
A3: ORD-10075 | B3: 45071 | C3: 45077 | D3: Nicholas Fischer Iii | E3: Corporate | F3: North | G3: Office Supplies | H3: Binders | I3: Whose Binders | J3: 2687.09 | K3: 6 | L3: 0 | M3: 210.34 | N3: =IF(Table3[[#This Row],[Profit]]<0,"Loss","Profit") -> Profit
A4: ORD-10590 | B4: 45074 | C4: 45080 | D4: Jeremy Norris | E4: Home Office | F4: East | G4: Furniture | H4: Bookcases | I4: Explain Bookcases | J4: 4308.83 | K4: 6 | L4: 0.15 | M4: 245.42 | N4: =IF(Table3[[#This Row],[Profit]]<0,"Loss","Profit") -> Profit
A5: ORD-10603 | B5: 45079 | C5: 45080 | D5: Tina Santos | E5: Corporate | F5: South | G5: Technology | H5: Accessories | I5: Consumer Accessories | J5: 653.71 | K5: 4 | L5: 0.15 | M5: 146.54 | N5: =IF(Table3[[#This Row],[Profit]]<0,"Loss","Profit") -> Profit
A6: ORD-10486 | B6: 45073 | C6: 45083 | D6: Rachel Santos | E6: Home Office | F6: North | G6: Technology | H6: Accessories | I6: Face Accessories | J6: 4783.14 | K6: 3 | L6: 0.15 | M6: -945.22 | N6: =IF(Table3[[#This Row],[Profit]]<0,"Loss","Profit") -> Loss
A7: ORD-10233 | B7: 45080 | C7: 45083 | D7: Margaret English | E7: Home Office | F7: East | G7: Office Supplies | H7: Paper | I7: Unit Paper | J7: 3050.99 | K7: 9 | L7: 0.05 | M7: -59.86 | N7: =IF(Table3[[#This Row],[Profit]]<0,"Loss","Profit") -> Loss
A8: ORD-10073 | B8: 45081 | C8: 45083 | D8: Patricia Rojas | E8: Corporate | F8: West | G8: Furniture | H8: Tables | I8: Despite Tables | J8: 2914.49 | K8: 5 | L8: 0.2 | M8: 502.87 | N8: =IF(Table3[[#This Row],[Profit]]<0,"Loss","Profit") -> Profit
A9: ORD-10261 | B9: 45084 | C9: 45086 | D9: Melissa Murphy | E9: Home Office | F9: South | G9: Furniture | H9: Bookcases | I9: Generation Bookcases | J9: 355.7 | K9: 9 | L9: 0.2 | M9: -31.59 | N9: =IF(Table3[[#This Row],[Profit]]<0,"Loss","Profit") -> Loss
A10: ORD-10595 | B10: 45087 | C10: 45088 | D10: Felicia Jones | E10: Corporate | F10: West | G10: Office Supplies | H10: Binders | I10: Quite Binders | J10: 2763.65 | K10: 4 | L10: 0.15 | M10: 788.16 | N10: =IF(Table3[[#This Row],[Profit]]<0,"Loss","Profit") -> Profit
A11: ORD-10288 | B11: 45088 | C11: 45089 | D11: Nicholas Castro | E11: Consumer | F11: West | G11: Furniture | H11: Bookcases | I11: Travel Bookcases | J11: 2643.52 | K11: 2 | L11: 0.2 | M11: -458.17 | N11: =IF(Table3[[#This Row],[Profit]]<0,"Loss","Profit") -> Loss
A12: ORD-10143 | B12: 45083 | C12: 45092 | D12: Sharon Scott | E12: Corporate | F12: West | G12: Office Supplies | H12: Binders | I12: Goal Binders | J12: 1543.07 | K12: 1 | L12: 0 | M12: 538.88 | N12: =IF(Table3[[#This Row],[Profit]]<0,"Loss","Profit") -> Profit
A13: ORD-10682 | B13: 45085 | C13: 45092 | D13: David Logan | E13: Home Office | F13: North | G13: Technology | H13: Laptops | I13: Yourself Laptops | J13: 2647 | K13: 4 | L13: 0.2 | M13: -444.69 | N13: =IF(Table3[[#This Row],[Profit]]<0,"Loss","Profit") -> Loss
... A73: ORD-10369 | B73: 45183 | C73: 45185 | D73: Elizabeth Park | E73: Consumer | F73: South | G73: Furniture | H73: Bookcases | I73: Thank Bookcases | J73: 1180.6 | K73: 9 | L73: 0 | M73: -207.52 | N73: =IF(Table3[[#This Row],[Profit]]<0,"Loss","Profit") -> Loss
A74: ORD-10187 | B74: 15-09-2023 | C74: 45185 | D74: Phyllis Arnold | E74: Consumer | F74: South | G74: Technology | H74: Phones | I74: Not Phones | J74: 1627.49 | K74: 2 | L74: 0.2 | M74: 256.29 | N74: =IF(Table3[[#This Row],[Profit]]<0,"Loss","Profit") -> Profit
A75: ORD-10222 | B75: 45184 | C75: 45188 | D75: Tiffany Young | E75: Corporate | F75: East | G75: Technology | H75: Accessories | I75: Specific Accessories | J75: 1733.95 | K75: 3 | L75: 0.1 | M75: 474.78 | N75: =IF(Table3[[#This Row],[Profit]]<0,"Loss","Profit") -> Profit
A76: ORD-10414 | B76: 45184 | C76: 45189 | D76: Kyle Sandoval | E76: Corporate | F76: South | G76: Office Supplies | H76: Paper | I76: Example Paper | J76: 1225.86 | K76: 1 | L76: 0.15 | M76: 140.33 | N76: =IF(Table3[[#This Row],[Profit]]<0,"Loss","Profit") -> Profit
A77: ORD-10287 | B77: 45182 | C77: 45190 | D77: Amanda Jones | E77: Home Office | F77: West | G77: Technology | H77: Accessories | I77: Skill Accessories | J77: 2331.1 | K77: 6 | L77: 0.05 | M77: -286.78 | N77: =IF(Table3[[#This Row],[Profit]]<0,"Loss","Profit") -> Loss
A78: ORD-10332 | B78: 45184 | C78: 45192 | D78: Danielle Morgan | E78: Home Office | F78: North | G78: Office Supplies | H78: Binders | I78: Difference Binders | J78: 1479.73 | K78: 3 | L78: 0.1 | M78: 389.3 | N78: =IF(Table3[[#This Row],[Profit]]<0,"Loss","Profit") -> Profit
A79: ORD-10062 | B79: 45190 | C79: 45192 | D79: John Potts | E79: Home Office | F79: South | G79: Technology | H79: Laptops | I79: Shake Laptops | J79: 734.95 | K79: 4 | L79: 0.15 | M79: 133.52 | N79: =IF(Table3[[#This Row],[Profit]]<0,"Loss","Profit") -> Profit
A80: ORD-10270 | B80: 45191 | C80: 45193 | D80: Robert Benitez | E80: Consumer | F80: South | G80: Technology | H80: Phones | I80: Environmental Phones | J80: 209.48 | K80: 7 | L80: 0.2 | M80: 46.36 | N80: =IF(Table3[[#This Row],[Profit]]<0,"Loss","Profit") -> Profit
A81: ORD-10077 | B81: 17-09-2023 | C81: 45195 | D81: William Gonzalez | E81: Home Office | F81: West | G81: Technology | H81: Phones | I81: Type Phones | J81: 4829.09 | K81: 5 | L81: 0.2 | M81: 1180.76 | N81: =IF(Table3[[#This Row],[Profit]]<0,"Loss","Profit") -> Profit
A82: ORD-10359 | B82: 45191 | C82: 45197 | D82: Joshua Costa | E82: Home Office | F82: West | G82: Office Supplies | H82: Binders | I82: End Binders | J82: 4672.93 | K82: 3 | L82: 0.15 | M82: 1277.8 | N82: =IF(Table3[[#This Row],[Profit]]<0,"Loss","Profit") -> Profit
A83: ORD-10251 | B83: 45194 | C83: 45199 | D83: Unknown | E83: Home Office | F83: West | G83: Furniture | H83: Chairs | I83: Marriage Chairs | J83: 2861.41 | K83: 2 | L83: 0.1 | M83: -124.45 | N83: =IF(Table3[[#This Row],[Profit]]<0,"Loss","Profit") -> Loss
A84: ORD-10601 | B84: 45195 | C84: 45200 | D84: Andrea Sandoval | E84: Consumer | F84: East | G84: Technology | H84: Accessories | I84: Rock Accessories | J84: 3939.34 | K84: 8 | L84: 0.1 | M84: 216.77 | N84: =IF(Table3[[#This Row],[Profit]]<0,"Loss","Profit") -> Profit
A85: ORD-10156 | B85: 45191 | C85: 45201 | D85: Unknown | E85: Home Office | F85: North | G85: Office Supplies | H85: Paper | I85: Able Paper | J85: 3001.31 | K85: 1 | L85: 0.05 | M85: -340.42 | N85: =IF(Table3[[#This Row],[Profit]]<0,"Loss","Profit") -> Loss
A86: ORD-10354 | B86: 45192 | C86: 45202 | D86: Christopher Kim | E86: Consumer | F86: West | G86: Furniture | H86: Bookcases | I86: Agency Bookcases | J86: 91.95 | K86: 3 | L86: 0.15 | M86: -0.63 | N86: =IF(Table3[[#This Row],[Profit]]<0,"Loss","Profit") -> Loss
A87: ORD-10182 | B87: 45198 | C87: 45202 | D87: Justin Jones | E87: Home Office | F87: West | G87: Furniture | H87: Bookcases | I87: Best Bookcases | J87: 1581.87 | K87: 8 | L87: 0.05 | M87: 3.66 | N87: =IF(Table3[[#This Row],[Profit]]<0,"Loss","Profit") -> Profit
A88: ORD-10223 | B88: 45197 | C88: 45203 | D88: Scott Miller | E88: Consumer | F88: East | G88: Technology | H88: Phones | I88: Until Phones | J88: 2599.15 | K88: 2 | L88: 0.1 | M88: -174.26 | N88: =IF(Table3[[#This Row],[Profit]]<0,"Loss","Profit") -> Loss
A89: ORD-10509 | B89: 45195 | C89: 45204 | D89: Stephanie Howard | E89: Consumer | F89: South | G89: Furniture | H89: Chairs | I89: Fight Chairs | J89: 4152.31 | K89: 7 | L89: 0.2 | M89: 1034.82 | N89: =IF(Table3[[#This Row],[Profit]]<0,"Loss","Profit") -> Profit
A90: ORD-10429 | B90: 45199 | C90: 45204 | D90: Michelle Hudson | E90: Consumer | F90: South | G90: Furniture | H90: Tables | I90: Still Tables | J90: 1589.2 | K90: 8 | L90: 0.2 | M90: 280.76 | N90: =IF(Table3[[#This Row],[Profit]]<0,"Loss","Profit") -> Profit
A91: ORD-10560 | B91: 45201 | C91: 45206 | D91: Thomas Nash | E91: Corporate | F91: South | G91: Furniture | H91: Bookcases | I91: Later Bookcases | J91: 3644.39 | K91: 9 | L91: 0.2 | M91: -31.15 | N91: =IF(Table3[[#This Row],[Profit]]<0,"Loss","Profit") -> Loss
A92: ORD-10614 | B92: 45201 | C92: 45206 | D92: Michael Blake | E92: Home Office | F92: West | G92: Technology | H92: Accessories | I92: Focus Accessories | J92: 2730.95 | K92: 8 | L92: 0 | M92: 619.26 | N92: =IF(Table3[[#This Row],[Profit]]<0,"Loss","Profit") -> Profit
A93: ORD-10497 | B93: 45201 | C93: 45208 | D93: Anne Cooper | E93: Home Office | F93: East | G93: Technology | H93: Accessories | I93: Church Accessories | J93: 4785.67 | K93: 6 | L93: 0.2 | M93: -815.52 | N93: =IF(Table3[[#This Row],[Profit]]<0,"Loss","Profit") -> Loss
... A117: ORD-10272 | B117: 45239 | C117: 45246 | D117: Eric Taylor | E117: Consumer | F117: South | G117: Office Supplies | H117: Binders | I117: Three Binders | J117: 2222.87 | K117: 9 | L117: 0.05 | M117: 477.72 | N117: =IF(Table3[[#This Row],[Profit]]<0,"Loss","Profit") -> Profit
A118: ORD-10037 | B118: 07-11-2023 | C118: 45246 | D118: Shannon Wagner | E118: Consumer | F118: South | G118: Office Supplies | H118: Storage | I118: With Storage | J118: 88.72 | K118: 9 | L118: 0.1 | M118: 27.72 | N118: =IF(Table3[[#This Row],[Profit]]<0,"Loss","Profit") -> Profit
A119: ORD-10582 | B119: 08-11-2023 | C119: 45247 | D119: Daniel Bowman | E119: Corporate | F119: West | G119: Technology | H119: Laptops | I119: Career Laptops | J119: 2463.09 | K119: 8 | L119: 0 | M119: 23.62 | N119: =IF(Table3[[#This Row],[Profit]]<0,"Loss","Profit") -> Profit
A120: ORD-10248 | B120: 45249 | C120: 45252 | D120: Samantha Briggs | E120: Corporate | F120: West | G120: Furniture | H120: Bookcases | I120: Painting Bookcases | J120: 75.65 | K120: 9 | L120: 0.05 | M120: 1.8 | N120: =IF(Table3[[#This Row],[Profit]]<0,"Loss","Profit") -> Profit
A121: ORD-10328 | B121: 45245 | C121: 45253 | D121: Christopher Jones | E121: Corporate | F121: North | G121: Furniture | H121: Tables | I121: Marriage Tables | J121: 2662.19 | K121: 6 | L121: 0.2 | M121: 36.61 | N121: =IF(Table3[[#This Row],[Profit]]<0,"Loss","Profit") -> Profit
A122: ORD-10266 | B122: 45250 | C122: 45253 | D122: Marcus Smith | E122: Corporate | F122: West | G122: Technology | H122: Accessories | I122: Such Accessories | J122: 3856.41 | K122: 7 | L122: 0.1 | M122: 1334.59 | N122: =IF(Table3[[#This Row],[Profit]]<0,"Loss","Profit") -> Profit
A123: ORD-10736 | B123: 45252 | C123: 45255 | D123: Joanna Weiss | E123: Corporate | F123: West | G123: Technology | H123: Phones | I123: New Phones | J123: 2997.94 | K123: 3 | L123: 0.15 | M123: 641.62 | N123: =IF(Table3[[#This Row],[Profit]]<0,"Loss","Profit") -> Profit
A124: ORD-10656 | B124: 45246 | C124: 45256 | D124: Jake Middleton | E124: Home Office | F124: North | G124: Technology | H124: Phones | I124: Choose Phones | J124: 4589.7 | K124: 6 | L124: 0 | M124: 488.97 | N124: =IF(Table3[[#This Row],[Profit]]<0,"Loss","Profit") -> Profit
A125: ORD-10617 | B125: 45254 | C125: 45260 | D125: Andrew Schneider | E125: Consumer | F125: South | G125: Technology | H125: Laptops | I125: When Laptops | J125: 596.8 | K125: 9 | L125: 0.2 | M125: -97.47 | N125: =IF(Table3[[#This Row],[Profit]]<0,"Loss","Profit") -> Loss
A126: ORD-10739 | B126: 45256 | C126: 45263 | D126: Jason Moss | E126: Consumer | F126: East | G126: Technology | H126: Laptops | I126: Couple Laptops | J126: 2399.22 | K126: 3 | L126: 0.2 | M126: 668.55 | N126: =IF(Table3[[#This Row],[Profit]]<0,"Loss","Profit") -> Profit
A127: ORD-10634 | B127: 45257 | C127: 45263 | D127: Keith Pham | E127: Consumer | F127: South | G127: Furniture | H127: Chairs | I127: Contain Chairs | J127: 1772.25 | K127: 7 | L127: 0.15 | M127: 552.3 | N127: =IF(Table3[[#This Row],[Profit]]<0,"Loss","Profit") -> Profit
A128: ORD-10708 | B128: 45257 | C128: 45263 | D128: Jacob Hammond | E128: Consumer | F128: West | G128: Office Supplies | H128: Storage | I128: My Storage | J128: 3954.45 | K128: 6 | L128: 0.15 | M128: 269.41 | N128: =IF(Table3[[#This Row],[Profit]]<0,"Loss","Profit") -> Profit
A129: ORD-10737 | B129: 45256 | C129: 45264 | D129: Unknown | E129: Corporate | F129: North | G129: Furniture | H129: Bookcases | I129: Raise Bookcases | J129: 3643.7 | K129: 3 | L129: 0.05 | M129: 429.11 | N129: =IF(Table3[[#This Row],[Profit]]<0,"Loss","Profit") -> Profit
A130: ORD-10469 | B130: 45257 | C130: 45265 | D130: Scott Collier | E130: Corporate | F130: South | G130: Technology | H130: Accessories | I130: Other Accessories | J130: 4777.69 | K130: 5 | L130: 0.2 | M130: -711.29 | N130: =IF(Table3[[#This Row],[Profit]]<0,"Loss","Profit") -> Loss
A131: ORD-10533 | B131: 45256 | C131: 45266 | D131: Anna Wood | E131: Consumer | F131: East | G131: Office Supplies | H131: Storage | I131: Nothing Storage | J131: 910.56 | K131: 7 | L131: 0.1 | M131: 112.2 | N131: =IF(Table3[[#This Row],[Profit]]<0,"Loss","Profit") -> Profit
... A166: ORD-10504 | B166: 45310 | C166: 45315 | D166: Dustin Shaw | E166: Home Office | F166: North | G166: Technology | H166: Accessories | I166: Country Accessories | J166: 1131.3 | K166: 10 | L166: 0.2 | M166: 69.2 | N166: =IF(Table3[[#This Row],[Profit]]<0,"Loss","Profit") -> Profit
A167: ORD-10668 | B167: 24-01-2024 | C167: 45317 | D167: Victor Allen | E167: Home Office | F167: South | G167: Office Supplies | H167: Paper | I167: Though Paper | J167: 3627.1 | K167: 2 | L167: 0.05 | M167: 828.07 | N167: =IF(Table3[[#This Row],[Profit]]<0,"Loss","Profit") -> Profit
A168: ORD-10184 | B168: 45310 | C168: 45318 | D168: Claire Farley | E168: Home Office | F168: North | G168: Technology | H168: Phones | I168: Suddenly Phones | J168: 4376.88 | K168: 9 | L168: 0 | M168: 837.17 | N168: =IF(Table3[[#This Row],[Profit]]<0,"Loss","Profit") -> Profit
A169: ORD-10702 | B169: 45310 | C169: 45319 | D169: Kimberly Dixon | E169: Home Office | F169: South | G169: Office Supplies | H169: Paper | I169: Paper Paper | J169: 1626.5 | K169: 3 | L169: 0.2 | M169: 393.94 | N169: =IF(Table3[[#This Row],[Profit]]<0,"Loss","Profit") -> Profit
A170: ORD-10053 | B170: 24-01-2024 | C170: 45320 | D170: Alexander Taylor | E170: Corporate | F170: East | G170: Office Supplies | H170: Storage | I170: History Storage | J170: 2060.07 | K170: 1 | L170: 0.1 | M170: -86.93 | N170: =IF(Table3[[#This Row],[Profit]]<0,"Loss","Profit") -> Loss
A171: ORD-10245 | B171: 45320 | C171: 45322 | D171: Lauren Robinson | E171: Corporate | F171: South | G171: Furniture | H171: Tables | I171: Paper Tables | J171: 1764.5 | K171: 8 | L171: 0.2 | M171: -104.03 | N171: =IF(Table3[[#This Row],[Profit]]<0,"Loss","Profit") -> Loss
A172: ORD-10194 | B172: 45321 | C172: 45322 | D172: Brett Lee | E172: Corporate | F172: North | G172: Technology | H172: Accessories | I172: Boy Accessories | J172: 3196.57 | K172: 6 | L172: 0.1 | M172: 674.55 | N172: =IF(Table3[[#This Row],[Profit]]<0,"Loss","Profit") -> Profit
A173: ORD-10208 | B173: 45321 | C173: 45328 | D173: Tammy Brown | E173: Home Office | F173: West | G173: Technology | H173: Laptops | I173: Our Laptops | J173: 4572.04 | K173: 2 | L173: 0.1 | M173: 1034.33 | N173: =IF(Table3[[#This Row],[Profit]]<0,"Loss","Profit") -> Profit
A174: ORD-10471 | B174: 45327 | C174: 45329 | D174: Samuel Butler | E174: Home Office | F174: West | G174: Office Supplies | H174: Binders | I174: Establish Binders | J174: 705.93 | K174: 1 | L174: 0.05 | M174: -100.92 | N174: =IF(Table3[[#This Row],[Profit]]<0,"Loss","Profit") -> Loss
A175: ORD-10365 | B175: 45321 | C175: 45331 | D175: Savannah Jackson | E175: Consumer | F175: North | G175: Technology | H175: Laptops | I175: Challenge Laptops | J175: 322.39 | K175: 3 | L175: 0 | M175: -62.23 | N175: =IF(Table3[[#This Row],[Profit]]<0,"Loss","Profit") -> Loss
A176: ORD-10298 | B176: 45328 | C176: 45332 | D176: Mary Barnes | E176: Home Office | F176: South | G176: Technology | H176: Phones | I176: Election Phones | J176: 2955.83 | K176: 7 | L176: 0 | M176: -104.63 | N176: =IF(Table3[[#This Row],[Profit]]<0,"Loss","Profit") -> Loss
A177: ORD-10397 | B177: 45329 | C177: 45332 | D177: David Rice | E177: Consumer | F177: West | G177: Office Supplies | H177: Storage | I177: Between Storage | J177: 2837.39 | K177: 4 | L177: 0.15 | M177: 278.54 | N177: =IF(Table3[[#This Row],[Profit]]<0,"Loss","Profit") -> Profit
A178: ORD-10227 | B178: 45335 | C178: 45336 | D178: Deanna White | E178: Home Office | F178: West | G178: Office Supplies | H178: Paper | I178: Day Paper | J178: 300.18 | K178: 8 | L178: 0.2 | M178: 85.64 | N178: =IF(Table3[[#This Row],[Profit]]<0,"Loss","Profit") -> Profit
A179: ORD-10723 | B179: 45329 | C179: 45337 | D179: Derrick Weber | E179: Corporate | F179: West | G179: Furniture | H179: Bookcases | I179: Agent Bookcases | J179: 3306.74 | K179: 3 | L179: 0 | M179: -411.78 | N179: =IF(Table3[[#This Row],[Profit]]<0,"Loss","Profit") -> Loss
A180: ORD-10559 | B180: 45330 | C180: 45337 | D180: Whitney Zimmerman | E180: Home Office | F180: North | G180: Technology | H180: Laptops | I180: Into Laptops | J180: 2056.98 | K180: 4 | L180: 0.2 | M180: -394.01 | N180: =IF(Table3[[#This Row],[Profit]]<0,"Loss","Profit") -> Loss
A181: ORD-10591 | B181: 45336 | C181: 45339 | D181: Lisa Nguyen | E181: Corporate | F181: West | G181: Office Supplies | H181: Paper | I181: Heavy Paper | J181: 4849.23 | K181: 9 | L181: 0.05 | M181: 605.95 | N181: =IF(Table3[[#This Row],[Profit]]<0,"Loss","Profit") -> Profit
A182: ORD-10006 | B182: 45335 | C182: 45340 | D182: Stephanie Rodriguez | E182: Home Office | F182: North | G182: Furniture | H182: Bookcases | I182: Task Bookcases | J182: 4155.55 | K182: 10 | L182: 0.1 | M182: 488.46 | N182: =IF(Table3[[#This Row],[Profit]]<0,"Loss","Profit") -> Profit
... A249: ORD-10027 | B249: 45441 | C249: 45444 | D249: Amanda Roy | E249: Home Office | F249: North | G249: Furniture | H249: Tables | I249: His Tables | J249: 1428.8 | K249: 4 | L249: 0 | M249: 62.47 | N249: =IF(Table3[[#This Row],[Profit]]<0,"Loss","Profit") -> Profit
A250: ORD-10426 | B250: 31-05-2024 | C250: 45448 | D250: Christy White | E250: Home Office | F250: West | G250: Office Supplies | H250: Binders | I250: New Binders | J250: 4344 | K250: 6 | L250: 0.15 | M250: -237.72 | N250: =IF(Table3[[#This Row],[Profit]]<0,"Loss","Profit") -> Loss
A251: ORD-10664 | B251: 45444 | C251: 45451 | D251: David Friedman | E251: Home Office | F251: North | G251: Office Supplies | H251: Paper | I251: Method Paper | J251: 3076.95 | K251: 10 | L251: 0.2 | M251: 291.96 | N251: =IF(Table3[[#This Row],[Profit]]<0,"Loss","Profit") -> Profit
A252: ORD-10540 | B252: 45447 | C252: 45452 | D252: Nichole Richardson | E252: Corporate | F252: West | G252: Office Supplies | H252: Storage | I252: His Storage | J252: 4738.91 | K252: 4 | L252: 0.15 | M252: 633.07 | N252: =IF(Table3[[#This Row],[Profit]]<0,"Loss","Profit") -> Profit
A253: ORD-10446 | B253: 45446 | C253: 45454 | D253: Jim Weiss | E253: Consumer | F253: East | G253: Technology | H253: Phones | I253: Own Phones | J253: 683.32 | K253: 5 | L253: 0.2 | M253: 167.13 | N253: =IF(Table3[[#This Row],[Profit]]<0,"Loss","Profit") -> Profit
A254: ORD-10101 | B254: 45449 | C254: 45456 | D254: Jacqueline Hernandez | E254: Corporate | F254: East | G254: Furniture | H254: Bookcases | I254: End Bookcases | J254: 3192.18 | K254: 8 | L254: 0 | M254: 186.76 | N254: =IF(Table3[[#This Row],[Profit]]<0,"Loss","Profit") -> Profit
A255: ORD-10492 | B255: 45452 | C255: 45458 | D255: Devin Young | E255: Home Office | F255: West | G255: Office Supplies | H255: Binders | I255: Music Binders | J255: 2833.29 | K255: 10 | L255: 0.2 | M255: 902.32 | N255: =IF(Table3[[#This Row],[Profit]]<0,"Loss","Profit") -> Profit
A256: ORD-10712 | B256: 45452 | C256: 45458 | D256: Daniel Kelly | E256: Corporate | F256: East | G256: Technology | H256: Phones | I256: Meeting Phones | J256: 1080.78 | K256: 10 | L256: 0.15 | M256: 250.06 | N256: =IF(Table3[[#This Row],[Profit]]<0,"Loss","Profit") -> Profit
A257: ORD-10415 | B257: 45457 | C257: 45458 | D257: Eric Hatfield | E257: Corporate | F257: South | G257: Furniture | H257: Tables | I257: Else Tables | J257: 2166.65 | K257: 5 | L257: 0.2 | M257: 311.56 | N257: =IF(Table3[[#This Row],[Profit]]<0,"Loss","Profit") -> Profit
A258: ORD-10726 | B258: 45456 | C258: 45461 | D258: Rebecca Daniel | E258: Consumer | F258: West | G258: Office Supplies | H258: Storage | I258: Director Storage | J258: 2083.65 | K258: 9 | L258: 0.2 | M258: 3.82 | N258: =IF(Table3[[#This Row],[Profit]]<0,"Loss","Profit") -> Profit
A259: ORD-10635 | B259: 45452 | C259: 45462 | D259: Eduardo West | E259: Consumer | F259: East | G259: Office Supplies | H259: Storage | I259: Simply Storage | J259: 4646.83 | K259: 7 | L259: 0 | M259: -150.41 | N259: =IF(Table3[[#This Row],[Profit]]<0,"Loss","Profit") -> Loss
A260: ORD-10637 | B260: 45452 | C260: 45462 | D260: Dean Alvarez | E260: Corporate | F260: South | G260: Technology | H260: Laptops | I260: Concern Laptops | J260: 2548.41 | K260: 4 | L260: 0.15 | M260: -103.51 | N260: =IF(Table3[[#This Row],[Profit]]<0,"Loss","Profit") -> Loss
A261: ORD-10289 | B261: 45458 | C261: 45462 | D261: Alexandra Pitts | E261: Corporate | F261: East | G261: Furniture | H261: Bookcases | I261: Several Bookcases | J261: 386.44 | K261: 3 | L261: 0 | M261: -30.8 | N261: =IF(Table3[[#This Row],[Profit]]<0,"Loss","Profit") -> Loss
A262: ORD-10553 | B262: 45457 | C262: 45465 | D262: Amy Watson | E262: Corporate | F262: East | G262: Office Supplies | H262: Binders | I262: Above Binders | J262: 3926.39 | K262: 3 | L262: 0 | M262: -322.15 | N262: =IF(Table3[[#This Row],[Profit]]<0,"Loss","Profit") -> Loss
... A310: ORD-10013 | B310: 45524 | C310: 45530 | D310: Kenneth Sullivan | E310: Consumer | F310: North | G310: Office Supplies | H310: Paper | I310: Example Paper | J310: 1135.64 | K310: 3 | L310: 0.2 | M310: 81.12 | N310: =IF(Table3[[#This Row],[Profit]]<0,"Loss","Profit") -> Profit
A311: ORD-10096 | B311: 17-08-2024 | C311: 45530 | D311: Kimberly Wood | E311: Consumer | F311: North | G311: Technology | H311: Phones | I311: Admit Phones | J311: 1162.81 | K311: 3 | L311: 0.1 | M311: 296.11 | N311: =IF(Table3[[#This Row],[Profit]]<0,"Loss","Profit") -> Profit
A312: ORD-10564 | B312: 45523 | C312: 45531 | D312: Robert Livingston | E312: Consumer | F312: South | G312: Office Supplies | H312: Binders | I312: Between Binders | J312: 625.53 | K312: 2 | L312: 0.15 | M312: 92.9 | N312: =IF(Table3[[#This Row],[Profit]]<0,"Loss","Profit") -> Profit
A313: ORD-10301 | B313: 45527 | C313: 45532 | D313: Wanda Graham | E313: Home Office | F313: West | G313: Technology | H313: Phones | I313: Relationship Phones | J313: 3928.56 | K313: 8 | L313: 0.15 | M313: -292.77 | N313: =IF(Table3[[#This Row],[Profit]]<0,"Loss","Profit") -> Loss
A314: ORD-10166 | B314: 45529 | C314: 45532 | D314: Stephen Andrews | E314: Home Office | F314: South | G314: Technology | H314: Accessories | I314: Stay Accessories | J314: 1219.53 | K314: 3 | L314: 0.1 | M314: -111.59 | N314: =IF(Table3[[#This Row],[Profit]]<0,"Loss","Profit") -> Loss
A315: ORD-10621 | B315: 45526 | C315: 45533 | D315: Kristina Kennedy | E315: Consumer | F315: North | G315: Office Supplies | H315: Storage | I315: Minute Storage | J315: 4119.03 | K315: 1 | L315: 0.2 | M315: -221.61 | N315: =IF(Table3[[#This Row],[Profit]]<0,"Loss","Profit") -> Loss
A316: ORD-10352 | B316: 45529 | C316: 45535 | D316: Ryan Williams | E316: Consumer | F316: South | G316: Furniture | H316: Chairs | I316: Whose Chairs | J316: 4094.69 | K316: 7 | L316: 0.2 | M316: -521.27 | N316: =IF(Table3[[#This Row],[Profit]]<0,"Loss","Profit") -> Loss
A317: ORD-10228 | B317: 45534 | C317: 45535 | D317: Michael Rivera | E317: Home Office | F317: East | G317: Technology | H317: Laptops | I317: Better Laptops | J317: 4243.5 | K317: 7 | L317: 0.05 | M317: 1210.89 | N317: =IF(Table3[[#This Row],[Profit]]<0,"Loss","Profit") -> Profit
A318: ORD-10316 | B318: 45529 | C318: 45537 | D318: Amy Carlson | E318: Home Office | F318: West | G318: Technology | H318: Laptops | I318: Growth Laptops | J318: 2932.11 | K318: 9 | L318: 0.2 | M318: 902.86 | N318: =IF(Table3[[#This Row],[Profit]]<0,"Loss","Profit") -> Profit
A319: ORD-10610 | B319: 45537 | C319: 45541 | D319: Jennifer Peterson | E319: Corporate | F319: South | G319: Furniture | H319: Tables | I319: Choose Tables | J319: 1617.86 | K319: 9 | L319: 0.2 | M319: 349.75 | N319: =IF(Table3[[#This Row],[Profit]]<0,"Loss","Profit") -> Profit
A320: ORD-10219 | B320: 45541 | C320: 45542 | D320: Victoria Smith | E320: Home Office | F320: West | G320: Furniture | H320: Chairs | I320: Memory Chairs | J320: 4745.31 | K320: 10 | L320: 0.1 | M320: 750.34 | N320: =IF(Table3[[#This Row],[Profit]]<0,"Loss","Profit") -> Profit
A321: ORD-10685 | B321: 45534 | C321: 45544 | D321: Laura Morrow | E321: Consumer | F321: West | G321: Technology | H321: Phones | I321: Affect Phones | J321: 1201.97 | K321: 5 | L321: 0.05 | M321: -239.35 | N321: =IF(Table3[[#This Row],[Profit]]<0,"Loss","Profit") -> Loss
A322: ORD-10201 | B322: 45539 | C322: 45546 | D322: Jonathon Chavez | E322: Corporate | F322: North | G322: Furniture | H322: Bookcases | I322: Want Bookcases | J322: 440.69 | K322: 10 | L322: 0.05 | M322: 44.07 | N322: =IF(Table3[[#This Row],[Profit]]<0,"Loss","Profit") -> Profit
A323: ORD-10308 | B323: 45543 | C323: 45546 | D323: Michael Jackson | E323: Consumer | F323: East | G323: Furniture | H323: Chairs | I323: Decade Chairs | J323: 2201.65 | K323: 7 | L323: 0.1 | M323: 146.03 | N323: =IF(Table3[[#This Row],[Profit]]<0,"Loss","Profit") -> Profit
... A352: ORD-10545 | B352: 45573 | C352: 45583 | D352: Sarah Sloan | E352: Home Office | F352: West | G352: Office Supplies | H352: Binders | I352: Forget Binders | J352: 2719.47 | K352: 1 | L352: 0.2 | M352: 427.17 | N352: =IF(Table3[[#This Row],[Profit]]<0,"Loss","Profit") -> Profit
A353: ORD-10294 | B353: 20-10-2024 | C353: 45587 | D353: Roberto Wells | E353: Corporate | F353: West | G353: Technology | H353: Laptops | I353: President Laptops | J353: 3285.99 | K353: 1 | L353: 0 | M353: 75.26 | N353: =IF(Table3[[#This Row],[Profit]]<0,"Loss","Profit") -> Profit
A354: ORD-10178 | B354: 45582 | C354: 45589 | D354: William Gonzalez | E354: Consumer | F354: East | G354: Office Supplies | H354: Storage | I354: Onto Storage | J354: 2567.02 | K354: 1 | L354: 0.1 | M354: -77.33 | N354: =IF(Table3[[#This Row],[Profit]]<0,"Loss","Profit") -> Loss
A355: ORD-10144 | B355: 45583 | C355: 45591 | D355: Stephanie Marshall | E355: Corporate | F355: South | G355: Office Supplies | H355: Binders | I355: Sister Binders | J355: 3576.39 | K355: 8 | L355: 0 | M355: 1053.59 | N355: =IF(Table3[[#This Row],[Profit]]<0,"Loss","Profit") -> Profit
A356: ORD-10413 | B356: 45588 | C356: 45592 | D356: Dawn Peterson | E356: Home Office | F356: East | G356: Furniture | H356: Tables | I356: They Tables | J356: 4873.27 | K356: 7 | L356: 0.2 | M356: 510.53 | N356: =IF(Table3[[#This Row],[Profit]]<0,"Loss","Profit") -> Profit
A357: ORD-10368 | B357: 45586 | C357: 45595 | D357: Samuel Wang | E357: Consumer | F357: East | G357: Technology | H357: Accessories | I357: Painting Accessories | J357: 1832.61 | K357: 8 | L357: 0.2 | M357: -198.32 | N357: =IF(Table3[[#This Row],[Profit]]<0,"Loss","Profit") -> Loss
...

Sheet pivot
A3: Row Labels | B3: Sum of Profit | D3: Row Labels | E3: Sum of Sales | G3: Row Labels | H3: Sum of Profit | J3: Row Labels | K3: Sum of Profit
A4: East | B4: 33519.38 | D4: East | E4: 503502.56 | G4: Consumer | H4: 38390.51 | J4: Furniture | K4: 52988.84
A5: North | B5: 25948.62 | D5: North | E5: 412491.76 | G5: Corporate | H5: 48388.25 | J5: Office Supplies | K5: 43084.21
A6: South | B6: 38760.63 | D6: South | E6: 433256.43 | G6: Home Office | H6: 53278.76 | J6: Technology | K6: 43984.47
A7: West | B7: 41828.89 | D7: West | E7: 531022.96 | G7: Grand Total | H7: 140057.52 | J7: Grand Total | K7: 140057.52
A8: Grand Total | B8: 140057.52 | D8: Grand Total | E8: 1880273.7
A11: Row Labels | B11: Count of Order ID | D11: Row Labels | E11: Sum of Sales | G11: Row Labels | H11: Sum of Profit
A12: East | B12: 192 | D12: Furniture | E12: 644115.56 | G12: East | H12: 33519.38
A13: North | B13: 166 | D13: Office Supplies | E13: 584271.08 | G13: Loss | H13: -18408.21
A14: South | B14: 182 | D14: Technology | E14: 651887.07 | G14: Profit | H14: 51927.59
A15: West | B15: 210 | D15: Grand Total | E15: 1880273.7 | G15: North | H15: 25948.62
A16: Grand Total | B16: 750 | G16: Loss | H16: -14358.46
G17: Profit | H17: 40307.08
G18: South | H18: 38760.63
G19: Loss | H19: -12181.6
G20: Profit | H20: 50942.23
G21: West | H21: 41828.89
G22: Loss | H22: -21336.52
G23: Profit | H23: 63165.41
G24: Grand Total | H24: 140057.52
